3/Diseno_Procesadores/Actividad_inicial/Multiplicador/componentes.v
`timescale 1 ns / 10 ps


// Registro de 4 bits, soporta Carga de entrada, reseteo y desplazamiento aritmético o lógico
// La línea de Carga indica que se va a asignar un nuevo valor al registro que viene por "entrada"
// La línea de Desplaza indica que se va a desplazar el contenido del registro. El bit más significativo se completa con la entrada "bit_en_desp"
module registro4 (input wire [3:0] entrada, input wire bit_en_desp, input wire Carga, Desplaza, clk, reset, output wire [3:0] salida);
  wire enable;

  assign enable = Carga | Desplaza; //Si se carga o desplaza se habilitan en modificación los biestables

  cdaff ff0(Carga, entrada[0], salida[1], clk, reset, enable, salida[0]);
  cdaff ff1(Carga, entrada[1], salida[2], clk, reset, enable, salida[1]);
  cdaff ff2(Carga, entrada[2], salida[3], clk, reset, enable, salida[2]);
  cdaff ff3(Carga, entrada[3], bit_en_desp, clk, reset, enable, salida[3]); //entra un bit en el desplaz
endmodule

// Registro de 3 bits, soporta Carga de entrada, reseteo y desplazamiento aritmético o lógico
// La línea de Carga indica que se va a asignar un nuevo valor al registro que viene por "entrada"
// La línea de Desplaza indica que se va a desplazar el contenido del registro. El bit más significativo se completa con la entrada "bit_en_desp"
module registro3 (input wire [2:0] entrada, input wire bit_en_desp, input wire Carga, Desplaza, clk, reset, output wire [2:0] salida);
  wire enable;
  
  assign enable = Carga | Desplaza; //Si se carga o desplaza se habilitan en modificación los biestables

  cdaff ff0(Carga, entrada[0], salida[1], clk, reset, enable, salida[0]);
  cdaff ff1(Carga, entrada[1], salida[2], clk, reset, enable, salida[1]);
  cdaff ff2(Carga, entrada[2], bit_en_desp, clk, reset, enable, salida[2]); //entra un bit en el desplaz
endmodule

//Biestable con entrada de mux para aceptar dos entradas posibles
module cdaff (input wire selc_d, inp_c, inp_d, clk, reset, carga, output wire salida);
  wire inp;
  
  ffdc ff0(clk, reset, carga, inp, salida);
  mux2_1_i1 mux0(inp, inp_d, inp_c, selc_d);
endmodule

//Mux de dos entradas de 1 bit realizado a partir de puertas 
module mux2_1_i1(output wire out, input wire a, b, s);
  //Declaración de conexiones internas
  wire  s_n, sa, sb;     
  //Instancias de puertas y sus conexiones
  not inv1 (s_n, s);
  and and1 (sa, a, s_n);
  and and2 (sb, b, s);
  or or1 (out, sa, sb);
endmodule

module ffdc #(parameter retardo = 0)(input wire clk, reset, carga, d, output reg q);
  //reset asíncrono, carga síncrona
  always @(posedge clk, posedge reset)
    if (reset)
      q <= #retardo 1'b0; //asignación no bloqueante q=0
    else
      if (carga)
        q <= #retardo d; //asignación no bloqueante q=d
endmodule

// Sumador/Restador de 4 bits
module sum_resta4(output wire[3:0] S, output wire c_out, input wire[3:0] A, input wire[3:0] B, input wire resta);
  assign {c_out, S} = (resta == 1) ? A - B + 0 : A + B + 0;
endmodule

3º/Diseno_Procesadores/Multiplicador/uc.v
module uc(input wire q0,qu, start, clk, input wire [3:0] M, A, input wire [2:0] Q, output wire CargaQ, CargaM, ResetA, CargaA, ResetQu, DesplazaA,Suma, Resta, Fin);
 reg[2:0] state, nextstate;
 
 parameter S0 = 3'b000;
 parameter S1 = 3'b001;
 parameter S2 = 3'b010;
 parameter S3 = 3'b011;
 parameter S4 = 3'b100;
 parameter S5 = 3'b101;
 parameter S6 = 3'b110;
 parameter S7 = 3'b111;
 
 always @(posedge clk, posedge start)
 if (start)
	state <= 0;
 else
	state <= nextstate;

 
 always @(*)
	case (state)
		S0: nextstate = S1;
		S1: nextstate = S2;
		S2: nextstate = S3;
		S3: nextstate = S4;
		S4: nextstate = S5;
		S5: nextstate = S6;
		S6: nextstate = S7;
		S7: nextstate = S7;
		default: nextstate = S0;
	endcase
  wire en_operacion = (state==S1) | (state==S3) | (state==S5);
		
	assign ResetA = (state == S0)? 1:0;
	assign ResetQu = (state == S0)? 1:0;
	assign CargaQ = (state == S0)? 1:0;
	assign CargaM = (state == S0)? 1:0;
	assign Resta = ((q0 == 1 & qu == 0) & (state == S1 | state == S3 | state == S5))? 1:0;
	assign Suma = ((~Resta) & (state == S1 | state == S3 | state == S5))? 1:0;
	assign CargaA = en_operacion & (q0 ^ qu);   // 01 o 10
	assign DesplazaA = ((state == S2) | (state == S4) | (state == S6))? 1:0;
	assign Fin = (state == S7)? 1:0;

endmodule

3º/Diseno_Procesadores/Multiplicador/multiplicador.v
module multiplicador(
  input wire [2:0] multiplicando, 
  input wire [2:0] multiplicador, 
  input wire clk, start, 
  output wire [5:0] resultado, 
  output wire fin);
 
// Cables de interconexión
wire Desplaza, CargaQ, CargaM, CargaA, Resta, Suma, ResetA, ResetQ_1;
wire [3:0] A_out, M_out, suma_out;
wire [2:0] Q_out;
wire Q_1_out;
wire c_out;

// TB envía 3 bits, pero Booth necesita un bit extra de seguridad (4 bits) para operaciones como -4 (100). Hacemos extensión de signo aquí dentro.
wire [3:0] mult_ext;
assign mult_ext = {multiplicando[2], multiplicando};

// Unidad de control
uc unidadcontrol(Q_out[0], Q_1_out, start, clk, M_out, A_out, Q_out, CargaQ, CargaM, ResetA, CargaA, ResetQ_1, Desplaza, Suma, Resta, fin);

// Registro A (Acumulador) de 4 bits
registro4 A_(suma_out, A_out[3], CargaA, Desplaza, clk, ResetA, A_out);
// Registro M (Multiplicando) de 4 bits
registro4 M_(mult_ext, 1'b0, CargaM, 1'b0, clk, 1'b0, M_out);
// Registro Q (Multiplicador) de 3 bits
registro3 Q_(multiplicador, A_out[0], CargaQ, Desplaza, clk, 1'b0, Q_out);
// Flip-Flop Q-1 (bit extra para Booth)
ffdc q1(clk, ResetQ_1, Desplaza, Q_out[0], Q_1_out);
// Sumador/Restador de 4 bits
sum_resta4 suma(suma_out, c_out, A_out, M_out, Resta);

// El resultado se obtiene concatenando el registro A con el registro Q
assign resultado = {A_out[2:0], Q_out};

endmodule

3º/Diseno_Procesadores/Multiplicador/multiplicador_tb.v
`timescale 1 ns / 10 ps
module multiplicador_tb;
//Recordar que el caso de -4 en tres bits en el multiplicando dará error en Booth si no hacemos que los registros A y M tengan un bit más (hay overflow) (depende de la implementación del sumador/restador)
parameter NUM_BITS = 3;
parameter NUM_TESTS = (2**(2*NUM_BITS));
parameter MAX_RANGE = (2**(NUM_BITS-1))-1;
parameter MIN_RANGE = - (2**(NUM_BITS-1));
integer contador;
reg clk, start;
wire Fin;
reg signed [NUM_BITS-1:0] multiplicador;
reg signed [NUM_BITS-1:0] multiplicando;
wire [(2*NUM_BITS)-1:0] resultado;
reg signed [(2*NUM_BITS)-1:0] resultado_esperado;

// generación de reloj clk
always //siempre activo, no hay condición de activación
begin
  clk = 1'b0;
  #5;
  clk = 1'b1;
  #5;
end

// Módulo a probar
multiplicador mult(multiplicando, multiplicador, clk, start, resultado, Fin);

initial
begin
  $dumpfile("multiplicador_tb.vcd");
  $dumpvars;
  #10000;   //Evita ejecución infinita
  $finish;
end

//Preparación caso inicial
initial
begin
  multiplicando = MIN_RANGE;
  multiplicador = MIN_RANGE;
  contador = 1;
end 

initial
begin
  start = 1'b1;
  #1;
  start = 1'b0;
end

always @(posedge Fin)
begin
  resultado_esperado = multiplicador * multiplicando;
  //Comprobación de resultados
  $write("%d x %d = %d", multiplicando, multiplicador, resultado_esperado);
  if (resultado !== resultado_esperado)
    $display("\tERROR    Obtenido=%b", resultado);
  else
    $display("\tCORRECTO Obtenido=%b", resultado);
  
  #20  //tiempo de espera entre una multiplicación y la siguiente
  if (contador == NUM_TESTS)
    $finish;
  else //Siguiente caso
  begin
    contador = contador + 1;
    if (multiplicador == MAX_RANGE)
    begin
      multiplicador = MIN_RANGE;
      multiplicando = multiplicando + 1;
    end
    else
    begin
      multiplicador = multiplicador + 1;
    end
    start = 1'b1;
    #1;
    start = 1'b0;           
  end
end

endmodule

3º/Diseno_Procesadores/Multiplicador/multiplicador_tb.vcd
$date
	Thu Feb 05 18:03:43 2026
$end
$version
	Icarus Verilog
$end
$timescale
	10ps
$end
$scope module multiplicador_tb $end
$var wire 6 ! resultado [5:0] $end
$var wire 1 " Fin $end
$var parameter 33 # MAX_RANGE $end
$var parameter 32 $ MIN_RANGE $end
$var parameter 32 % NUM_BITS $end
$var parameter 32 & NUM_TESTS $end
$var reg 1 ' clk $end
$var reg 3 ( multiplicador [2:0] $end
$var reg 3 ) multiplicando [2:0] $end
$var reg 6 * resultado_esperado [5:0] $end
$var reg 1 + start $end
$var integer 32 , contador [31:0] $end
$scope module mult $end
$var wire 1 ' clk $end
$var wire 3 - multiplicador [2:0] $end
$var wire 3 . multiplicando [2:0] $end
$var wire 1 + start $end
$var wire 4 / suma_out [3:0] $end
$var wire 6 0 resultado [5:0] $end
$var wire 4 1 mult_ext [3:0] $end
$var wire 1 " fin $end
$var wire 1 2 c_out $end
$var wire 1 3 Suma $end
$var wire 1 4 Resta $end
$var wire 1 5 ResetQ_1 $end
$var wire 1 6 ResetA $end
$var wire 3 7 Q_out [2:0] $end
$var wire 1 8 Q_1_out $end
$var wire 4 9 M_out [3:0] $end
$var wire 1 : Desplaza $end
$var wire 1 ; CargaQ $end
$var wire 1 < CargaM $end
$var wire 1 = CargaA $end
$var wire 4 > A_out [3:0] $end
$scope module A_ $end
$var wire 1 ? bit_en_desp $end
$var wire 1 ' clk $end
$var wire 1 @ enable $end
$var wire 4 A salida [3:0] $end
$var wire 1 6 reset $end
$var wire 4 B entrada [3:0] $end
$var wire 1 : Desplaza $end
$var wire 1 = Carga $end
$scope module ff0 $end
$var wire 1 @ carga $end
$var wire 1 ' clk $end
$var wire 1 C inp_c $end
$var wire 1 D inp_d $end
$var wire 1 = selc_d $end
$var wire 1 E salida $end
$var wire 1 6 reset $end
$var wire 1 F inp $end
$scope module ff0 $end
$var wire 1 @ carga $end
$var wire 1 ' clk $end
$var wire 1 6 reset $end
$var wire 1 F d $end
$var parameter 32 G retardo $end
$var reg 1 E q $end
$upscope $end
$scope module mux0 $end
$var wire 1 D a $end
$var wire 1 C b $end
$var wire 1 F out $end
$var wire 1 H s_n $end
$var wire 1 I sa $end
$var wire 1 J sb $end
$var wire 1 = s $end
$upscope $end
$upscope $end
$scope module ff1 $end
$var wire 1 @ carga $end
$var wire 1 ' clk $end
$var wire 1 K inp_c $end
$var wire 1 L inp_d $end
$var wire 1 = selc_d $end
$var wire 1 M salida $end
$var wire 1 6 reset $end
$var wire 1 N inp $end
$scope module ff0 $end
$var wire 1 @ carga $end
$var wire 1 ' clk $end
$var wire 1 6 reset $end
$var wire 1 N d $end
$var parameter 32 O retardo $end
$var reg 1 M q $end
$upscope $end
$scope module mux0 $end
$var wire 1 L a $end
$var wire 1 K b $end
$var wire 1 N out $end
$var wire 1 P s_n $end
$var wire 1 Q sa $end
$var wire 1 R sb $end
$var wire 1 = s $end
$upscope $end
$upscope $end
$scope module ff2 $end
$var wire 1 @ carga $end
$var wire 1 ' clk $end
$var wire 1 S inp_c $end
$var wire 1 T inp_d $end
$var wire 1 = selc_d $end
$var wire 1 U salida $end
$var wire 1 6 reset $end
$var wire 1 V inp $end
$scope module ff0 $end
$var wire 1 @ carga $end
$var wire 1 ' clk $end
$var wire 1 6 reset $end
$var wire 1 V d $end
$var parameter 32 W retardo $end
$var reg 1 U q $end
$upscope $end
$scope module mux0 $end
$var wire 1 T a $end
$var wire 1 S b $end
$var wire 1 V out $end
$var wire 1 X s_n $end
$var wire 1 Y sa $end
$var wire 1 Z sb $end
$var wire 1 = s $end
$upscope $end
$upscope $end
$scope module ff3 $end
$var wire 1 @ carga $end
$var wire 1 ' clk $end
$var wire 1 [ inp_c $end
$var wire 1 ? inp_d $end
$var wire 1 = selc_d $end
$var wire 1 \ salida $end
$var wire 1 6 reset $end
$var wire 1 ] inp $end
$scope module ff0 $end
$var wire 1 @ carga $end
$var wire 1 ' clk $end
$var wire 1 6 reset $end
$var wire 1 ] d $end
$var parameter 32 ^ retardo $end
$var reg 1 \ q $end
$upscope $end
$scope module mux0 $end
$var wire 1 ? a $end
$var wire 1 [ b $end
$var wire 1 ] out $end
$var wire 1 _ s_n $end
$var wire 1 ` sa $end
$var wire 1 a sb $end
$var wire 1 = s $end
$upscope $end
$upscope $end
$upscope $end
$scope module M_ $end
$var wire 1 b Desplaza $end
$var wire 1 c bit_en_desp $end
$var wire 1 ' clk $end
$var wire 1 d enable $end
$var wire 4 e entrada [3:0] $end
$var wire 1 f reset $end
$var wire 4 g salida [3:0] $end
$var wire 1 < Carga $end
$scope module ff0 $end
$var wire 1 d carga $end
$var wire 1 ' clk $end
$var wire 1 h inp_c $end
$var wire 1 i inp_d $end
$var wire 1 f reset $end
$var wire 1 < selc_d $end
$var wire 1 j salida $end
$var wire 1 k inp $end
$scope module ff0 $end
$var wire 1 d carga $end
$var wire 1 ' clk $end
$var wire 1 f reset $end
$var wire 1 k d $end
$var parameter 32 l retardo $end
$var reg 1 j q $end
$upscope $end
$scope module mux0 $end
$var wire 1 i a $end
$var wire 1 h b $end
$var wire 1 k out $end
$var wire 1 m s_n $end
$var wire 1 n sa $end
$var wire 1 o sb $end
$var wire 1 < s $end
$upscope $end
$upscope $end
$scope module ff1 $end
$var wire 1 d carga $end
$var wire 1 ' clk $end
$var wire 1 p inp_c $end
$var wire 1 q inp_d $end
$var wire 1 f reset $end
$var wire 1 < selc_d $end
$var wire 1 r salida $end
$var wire 1 s inp $end
$scope module ff0 $end
$var wire 1 d carga $end
$var wire 1 ' clk $end
$var wire 1 f reset $end
$var wire 1 s d $end
$var parameter 32 t retardo $end
$var reg 1 r q $end
$upscope $end
$scope module mux0 $end
$var wire 1 q a $end
$var wire 1 p b $end
$var wire 1 s out $end
$var wire 1 u s_n $end
$var wire 1 v sa $end
$var wire 1 w sb $end
$var wire 1 < s $end
$upscope $end
$upscope $end
$scope module ff2 $end
$var wire 1 d carga $end
$var wire 1 ' clk $end
$var wire 1 x inp_c $end
$var wire 1 y inp_d $end
$var wire 1 f reset $end
$var wire 1 < selc_d $end
$var wire 1 z salida $end
$var wire 1 { inp $end
$scope module ff0 $end
$var wire 1 d carga $end
$var wire 1 ' clk $end
$var wire 1 f reset $end
$var wire 1 { d $end
$var parameter 32 | retardo $end
$var reg 1 z q $end
$upscope $end
$scope module mux0 $end
$var wire 1 y a $end
$var wire 1 x b $end
$var wire 1 { out $end
$var wire 1 } s_n $end
$var wire 1 ~ sa $end
$var wire 1 !" sb $end
$var wire 1 < s $end
$upscope $end
$upscope $end
$scope module ff3 $end
$var wire 1 d carga $end
$var wire 1 ' clk $end
$var wire 1 "" inp_c $end
$var wire 1 c inp_d $end
$var wire 1 f reset $end
$var wire 1 < selc_d $end
$var wire 1 #" salida $end
$var wire 1 $" inp $end
$scope module ff0 $end
$var wire 1 d carga $end
$var wire 1 ' clk $end
$var wire 1 f reset $end
$var wire 1 $" d $end
$var parameter 32 %" retardo $end
$var reg 1 #" q $end
$upscope $end
$scope module mux0 $end
$var wire 1 c a $end
$var wire 1 "" b $end
$var wire 1 $" out $end
$var wire 1 &" s_n $end
$var wire 1 '" sa $end
$var wire 1 (" sb $end
$var wire 1 < s $end
$upscope $end
$upscope $end
$upscope $end
$scope module Q_ $end
$var wire 1 )" bit_en_desp $end
$var wire 1 ' clk $end
$var wire 1 *" enable $end
$var wire 3 +" entrada [2:0] $end
$var wire 1 ," reset $end
$var wire 3 -" salida [2:0] $end
$var wire 1 : Desplaza $end
$var wire 1 ; Carga $end
$scope module ff0 $end
$var wire 1 *" carga $end
$var wire 1 ' clk $end
$var wire 1 ." inp_c $end
$var wire 1 /" inp_d $end
$var wire 1 ," reset $end
$var wire 1 ; selc_d $end
$var wire 1 0" salida $end
$var wire 1 1" inp $end
$scope module ff0 $end
$var wire 1 *" carga $end
$var wire 1 ' clk $end
$var wire 1 ," reset $end
$var wire 1 1" d $end
$var parameter 32 2" retardo $end
$var reg 1 0" q $end
$upscope $end
$scope module mux0 $end
$var wire 1 /" a $end
$var wire 1 ." b $end
$var wire 1 1" out $end
$var wire 1 3" s_n $end
$var wire 1 4" sa $end
$var wire 1 5" sb $end
$var wire 1 ; s $end
$upscope $end
$upscope $end
$scope module ff1 $end
$var wire 1 *" carga $end
$var wire 1 ' clk $end
$var wire 1 6" inp_c $end
$var wire 1 7" inp_d $end
$var wire 1 ," reset $end
$var wire 1 ; selc_d $end
$var wire 1 8" salida $end
$var wire 1 9" inp $end
$scope module ff0 $end
$var wire 1 *" carga $end
$var wire 1 ' clk $end
$var wire 1 ," reset $end
$var wire 1 9" d $end
$var parameter 32 :" retardo $end
$var reg 1 8" q $end
$upscope $end
$scope module mux0 $end
$var wire 1 7" a $end
$var wire 1 6" b $end
$var wire 1 9" out $end
$var wire 1 ;" s_n $end
$var wire 1 <" sa $end
$var wire 1 =" sb $end
$var wire 1 ; s $end
$upscope $end
$upscope $end
$scope module ff2 $end
$var wire 1 *" carga $end
$var wire 1 ' clk $end
$var wire 1 >" inp_c $end
$var wire 1 )" inp_d $end
$var wire 1 ," reset $end
$var wire 1 ; selc_d $end
$var wire 1 ?" salida $end
$var wire 1 @" inp $end
$scope module ff0 $end
$var wire 1 *" carga $end
$var wire 1 ' clk $end
$var wire 1 ," reset $end
$var wire 1 @" d $end
$var parameter 32 A" retardo $end
$var reg 1 ?" q $end
$upscope $end
$scope module mux0 $end
$var wire 1 )" a $end
$var wire 1 >" b $end
$var wire 1 @" out $end
$var wire 1 B" s_n $end
$var wire 1 C" sa $end
$var wire 1 D" sb $end
$var wire 1 ; s $end
$upscope $end
$upscope $end
$upscope $end
$scope module q1 $end
$var wire 1 ' clk $end
$var wire 1 E" d $end
$var wire 1 5 reset $end
$var wire 1 : carga $end
$var parameter 32 F" retardo $end
$var reg 1 8 q $end
$upscope $end
$scope module suma $end
$var wire 4 G" A [3:0] $end
$var wire 4 H" B [3:0] $end
$var wire 1 4 resta $end
$var wire 1 2 c_out $end
$var wire 4 I" S [3:0] $end
$upscope $end
$scope module unidadcontrol $end
$var wire 4 J" A [3:0] $end
$var wire 1 = CargaA $end
$var wire 4 K" M [3:0] $end
$var wire 3 L" Q [2:0] $end
$var wire 1 ' clk $end
$var wire 1 M" en_operacion $end
$var wire 1 N" q0 $end
$var wire 1 8 qu $end
$var wire 1 + start $end
$var wire 1 3 Suma $end
$var wire 1 4 Resta $end
$var wire 1 5 ResetQu $end
$var wire 1 6 ResetA $end
$var wire 1 " Fin $end
$var wire 1 : DesplazaA $end
$var wire 1 ; CargaQ $end
$var wire 1 < CargaM $end
$var parameter 3 O" S0 $end
$var parameter 3 P" S1 $end
$var parameter 3 Q" S2 $end
$var parameter 3 R" S3 $end
$var parameter 3 S" S4 $end
$var parameter 3 T" S5 $end
$var parameter 3 U" S6 $end
$var parameter 3 V" S7 $end
$var reg 3 W" nextstate [2:0] $end
$var reg 3 X" state [2:0] $end
$upscope $end
$upscope $end
$upscope $end
$enddefinitions $end
$comment Show the parameter values. $end
$dumpall
b111 V"
b110 U"
b101 T"
b100 S"
b11 R"
b10 Q"
b1 P"
b0 O"
b0 F"
b0 A"
b0 :"
b0 2"
b0 %"
b0 |
b0 t
b0 l
b0 ^
b0 W
b0 O
b0 G
b1000000 &
b11 %
b11111111111111111111111111111100 $
b11 #
$end
#0
$dumpvars
b0 X"
b1 W"
xN"
0M"
bx L"
bx K"
b0 J"
bx I"
bx H"
b0 G"
xE"
1D"
0C"
0B"
1@"
x?"
1>"
0="
0<"
0;"
09"
x8"
x7"
06"
05"
04"
03"
01"
x0"
x/"
0."
bx -"
0,"
b100 +"
1*"
0)"
1("
0'"
0&"
1$"
x#"
1""
1!"
0~
0}
1{
xz
xy
1x
0w
0v
0u
0s
xr
xq
0p
0o
0n
0m
0k
xj
xi
0h
bx g
0f
b1100 e
1d
0c
0b
0a
0`
1_
0]
0\
x[
0Z
0Y
1X
0V
0U
0T
xS
0R
0Q
1P
0N
0M
0L
xK
0J
0I
1H
0F
0E
0D
xC
bx B
b0 A
0@
0?
b0 >
0=
1<
1;
0:
bx 9
08
bx 7
16
15
04
03
x2
b1100 1
b0xxx 0
bx /
b100 .
b100 -
b1 ,
1+
bx *
b100 )
b100 (
0'
0"
b0xxx !
$end
#100
0+
#500
19"
1s
13
0@"
1<"
0$"
1~
1v
1[
1S
0K
0C
0D"
1B"
1;"
13"
0*"
0("
1&"
0!"
1}
1u
1m
0d
b1100 /
b1100 B
b1100 I"
02
1M"
06
05
0;
0<
0i
1q
1y
0E"
0N"
0/"
17"
b10 W"
0j
0r
1z
b1100 9
b1100 g
b1100 H"
b1100 K"
1#"
00"
08"
b100 !
b100 0
b100 7
b100 -"
b100 L"
1?"
b1 X"
1'
#1000
0'
#1500
03
1*"
1@
1:
0M"
b11 W"
b10 X"
1'
#2000
0'
#2500
13
0*"
0@
0:
11"
09"
14"
0<"
1M"
1/"
07"
b100 W"
18"
b10 !
b10 0
b10 7
b10 -"
b10 L"
0?"
b11 X"
1'
#3000
0'
#3500
03
1*"
1@
1:
0M"
b101 W"
b100 X"
1'
#4000
0'
#4500
0[
b100 /
b100 B
b100 I"
12
0]
1V
14
0*"
0a
0_
1Z
0X
0P
0H
03
0:
1=
01"
04"
1E"
1N"
0/"
b110 W"
1M"
10"
b1 !
b1 0
b1 7
b1 -"
b1 L"
08"
b101 X"
1'
#5000
0'
#5500
1N
0V
1Q
04
1*"
0[
0S
1_
0Z
1X
1P
1H
1:
b0 /
b0 B
b0 I"
0=
1L
b100001 !
b100001 0
b111 W"
0M"
b100 >
b100 A
b100 G"
b100 J"
1U
b110 X"
1'
#6000
0'
#6500
0*"
0@
0N
1[
1S
1K
1F
0:
b10000 *
0Q
b1110 /
b1110 B
b1110 I"
02
1I
1"
0L
1D
0E"
0N"
0U
b10 >
b10 A
b10 G"
b10 J"
1M
b10000 !
b10000 0
b0 7
b0 -"
b0 L"
00"
18
b111 X"
1'
#7000
0'
#7500
1'
#8000
0'
#8500
0K
0F
b1100 /
b1100 B
b1100 I"
0I
0D
b0 !
b0 0
b0 >
b0 A
b0 G"
b0 J"
0M
08
0s
1@"
11"
1$"
0~
0v
1D"
0B"
0;"
15"
03"
1*"
1("
0&"
1!"
0}
0u
0m
1d
16
15
1;
1<
0"
b1 W"
b0 X"
1."
1'
1+
b101 (
b101 -
b101 +"
b10 ,
#8600
0+
#9000
0'
#9500
0[
b100 /
b100 B
b100 I"
12
0]
1V
19"
1s
14
03
0a
0_
1Z
0X
0P
0H
1@
0@"
1<"
01"
0$"
1~
1v
1=
0D"
1B"
1;"
05"
13"
0*"
0("
1&"
0!"
1}
1u
1m
0d
1M"
06
05
0;
0<
17"
1E"
1N"
b10 W"
1?"
b101 !
b101 0
b101 7
b101 -"
b101 L"
10"
b1 X"
1'
#10000
0'
#10500
1N
0V
1Q
04
1*"
1_
0Z
1X
1P
1H
1:
0[
0S
0=
b0 /
b0 B
b0 I"
0M"
1L
b100101 !
b100101 0
b11 W"
b100 >
b100 A
b100 G"
b100 J"
1U
b10 X"
1'
#11000
0'
#11500
1]
1V
13
0*"
1a
0_
1Z
0X
1R
0P
0H
0:
1N
1[
1S
1K
0F
09"
11"
1=
0Q
b1110 /
b1110 B
b1110 I"
02
0I
0<"
14"
1M"
0L
1D
07"
1/"
0E"
0N"
b100 W"
0U
b10 >
b10 A
b10 G"
b10 J"
1M
0?"
18"
b10010 !
b10010 0
b10 7
b10 -"
b10 L"
00"
18
b11 X"
1'
#12000
0'
#12500
1F
1`
1Y
1Q
1I
03
1*"
0a
1_
0Z
1X
0R
1P
1H
1:
0S
0=
b1010 /
b1010 B
b1010 I"
12
0M"
1L
b110010 !
b110010 0
1T
1?
b101 W"
1U
b1110 >
b1110 A
b1110 G"
b1110 J"
1\
b100 X"
1'
#13000
0'
#13500
0]
0[
02
0V
0`
0Y
0Q
0I
14
0*"
0a
0_
0X
1R
0P
1J
0H
03
0:
1C
1@"
01"
1=
b11 /
b11 B
b11 I"
1C"
04"
1)"
0/"
1E"
1N"
b110 W"
1M"
b1111 >
b1111 A
b1111 G"
b1111 J"
1E
08"
b111001 !
b111001 0
b1 7
b1 -"
b1 L"
10"
08
b101 X"
1'
#14000
0'
#14500
1[
0N
1I
04
1*"
1S
1_
1X
0R
1P
0J
1H
1:
b1111 /
b1111 B
b1111 I"
02
0=
0L
b11001 !
b11001 0
0T
0?
b111 W"
0M"
0U
b11 >
b11 A
b11 G"
b11 J"
0\
b110 X"
1'
#15000
0'
#15500
0*"
0@
0K
0F
19"
0:
b1100 *
b1101 /
b1101 B
b1101 I"
0I
1<"
1"
0D
17"
0E"
0N"
b1 >
b1 A
b1 G"
b1 J"
0M
1?"
b1100 !
b1100 0
b100 7
b100 -"
b100 L"
00"
18
b111 X"
1'
#16000
0'
#16500
1'
#17000
0'
#17500
0C
b1100 /
b1100 B
b1100 I"
b100 !
b100 0
0)"
b0 >
b0 A
b0 G"
b0 J"
0E
08
0s
0C"
0<"
1$"
0~
0v
1D"
0B"
1="
0;"
03"
1*"
1("
0&"
1!"
0}
0u
0m
1d
16
15
1;
1<
0"
b1 W"
b0 X"
0."
16"
1'
1+
b110 (
b110 -
b110 +"
b11 ,
#17600
0+
#18000
0'
#18500
11"
1s
13
0@"
1<"
14"
0$"
1~
1v
0D"
1B"
0="
1;"
13"
0*"
0("
1&"
0!"
1}
1u
1m
0d
1M"
06
05
0;
0<
1/"
b10 W"
b110 !
b110 0
b110 7
b110 -"
b110 L"
18"
b1 X"
1'
#19000
0'
#19500
03
1*"
1@
1:
0M"
b11 W"
b10 X"
1'
#20000
0'
#20500
0[
b100 /
b100 B
b100 I"
12
0]
1V
14
03
0*"
0a
0_
1Z
0X
0P
0H
0:
09"
1=
0<"
1M"
1E"
1N"
07"
b100 W"
10"
b11 !
b11 0
b11 7
b11 -"
b11 L"
0?"
b11 X"
1'
#21000
0'
#21500
1N
0V
1Q
04
1*"
1_
0Z
1X
1P
1H
1:
0[
0S
0=
b0 /
b0 B
b0 I"
0M"
1L
b100011 !
b100011 0
b101 W"
b100 >
b100 A
b100 G"
b100 J"
1U
b100 X"
1'
#22000
0'
#22500
0*"
0@
13
0:
0N
1[
1S
1K
1F
01"
0Q
b1110 /
b1110 B
b1110 I"
02
1I
04"
0L
1D
0/"
b110 W"
1M"
0U
b10 >
b10 A
b10 G"
b10 J"
1M
b10001 !
b10001 0
b1 7
b1 -"
b1 L"
08"
18
b101 X"
1'
#23000
0'
#23500
03
1*"
1@
1:
b111 W"
0M"
b110 X"
1'
#24000
0'
#24500
0*"
0@
0F
0K
1C
1@"
0:
b1000 *
0I
b1101 /
b1101 B
b1101 I"
1C"
1"
0D
1)"
0E"
0N"
0M
b1 >
b1 A
b1 G"
b1 J"
1E
b1000 !
b1000 0
b0 7
b0 -"
b0 L"
00"
b111 X"
1'
#25000
0'
#25500
1'
#26000
0'
#26500
0C
b1100 /
b1100 B
b1100 I"
b0 !
b0 0
0)"
b0 >
b0 A
b0 G"
b0 J"
0E
08
0s
0C"
19"
11"
1$"
0~
0v
1D"
0B"
1="
0;"
15"
03"
1*"
1("
0&"
1!"
0}
0u
0m
1d
16
15
1;
1<
0"
b1 W"
b0 X"
1."
1'
1+
b111 (
b111 -
b111 +"
b100 ,
#26600
0+
#27000
0'
#27500
0[
b100 /
b100 B
b100 I"
12
0]
1V
1s
14
03
0a
0_
1Z
0X
0P
0H
1@
0@"
1<"
14"
0$"
1~
1v
1=
0D"
1B"
0="
1;"
05"
13"
0*"
0("
1&"
0!"
1}
1u
1m
0d
1M"
06
05
0;
0<
17"
1/"
1E"
1N"
b10 W"
1?"
18"
b111 !
b111 0
b111 7
b111 -"
b111 L"
10"
b1 X"
1'
#28000
0'
#28500
1N
0V
1Q
04
1*"
1_
0Z
1X
1P
1H
1:
0[
0S
0=
b0 /
b0 B
b0 I"
0M"
1L
b100111 !
b100111 0
b11 W"
b100 >
b100 A
b100 G"
b100 J"
1U
b10 X"
1'
#29000
0'
#29500
13
0*"
0@
0:
0N
1[
1S
1K
1F
09"
0Q
b1110 /
b1110 B
b1110 I"
02
1I
0<"
1M"
0L
1D
07"
b100 W"
0U
b10 >
b10 A
b10 G"
b10 J"
1M
b10011 !
b10011 0
b11 7
b11 -"
b11 L"
0?"
18
b11 X"
1'
#30000
0'
#30500
03
1*"
1@
1:
0M"
b101 W"
b100 X"
1'
#31000
0'
#31500
0*"
0@
13
0:
0F
0K
1C
1@"
01"
0I
b1101 /
b1101 B
b1101 I"
1C"
04"
0D
1)"
0/"
b110 W"
1M"
0M
b1 >
b1 A
b1 G"
b1 J"
1E
b1001 !
b1001 0
b1 7
b1 -"
b1 L"
08"
b101 X"
1'
#32000
0'
#32500
03
1*"
1@
1:
b111 W"
0M"
b110 X"
1'
#33000
0'
#33500
0*"
0@
0C
0@"
19"
0:
b100 *
b1100 /
b1100 B
b1100 I"
0C"
1<"
1"
0)"
17"
0E"
0N"
b0 >
b0 A
b0 G"
b0 J"
0E
1?"
b100 !
b100 0
b100 7
b100 -"
b100 L"
00"
b111 X"
1'
#34000
0'
#34500
1'
#35000
0'
#35500
08
09"
0s
0<"
1$"
0~
0v
0B"
0;"
03"
1*"
1("
0&"
1!"
0}
0u
0m
1d
16
15
1;
1<
0"
b1 W"
b0 X"
0."
06"
0>"
1'
1+
b0 (
b0 -
b0 +"
b101 ,
#35600
0+
#36000
0'
#36500
1s
13
0$"
1~
1v
1B"
1;"
13"
0*"
0("
1&"
0!"
1}
1u
1m
0d
1M"
06
05
0;
0<
07"
b10 W"
b0 !
b0 0
b0 7
b0 -"
b0 L"
0?"
b1 X"
1'
#37000
0'
#37500
03
1*"
1@
1:
0M"
b11 W"
b10 X"
1'
#38000
0'
#38500
13
0*"
0@
0:
1M"
b100 W"
b11 X"
1'
#39000
0'
#39500
03
1*"
1@
1:
0M"
b101 W"
b100 X"
1'
#40000
0'
