3/Diseno_Procesadores/Actividad_inicial/Multiplicador/componentes.v
`timescale 1 ns / 10 ps


// Registro de 4 bits, soporta Carga de entrada, reseteo y desplazamiento aritmético o lógico
// La línea de Carga indica que se va a asignar un nuevo valor al registro que viene por "entrada"
// La línea de Desplaza indica que se va a desplazar el contenido del registro. El bit más significativo se completa con la entrada "bit_en_desp"
module registro4 (input wire [3:0] entrada, input wire bit_en_desp, input wire Carga, Desplaza, clk, reset, output wire [3:0] salida);
  wire enable;

  assign enable = Carga | Desplaza; //Si se carga o desplaza se habilitan en modificación los biestables

  cdaff ff0(Carga, entrada[0], salida[1], clk, reset, enable, salida[0]);
  cdaff ff1(Carga, entrada[1], salida[2], clk, reset, enable, salida[1]);
  cdaff ff2(Carga, entrada[2], salida[3], clk, reset, enable, salida[2]);
  cdaff ff3(Carga, entrada[3], bit_en_desp, clk, reset, enable, salida[3]); //entra un bit en el desplaz
endmodule

// Registro de 3 bits, soporta Carga de entrada, reseteo y desplazamiento aritmético o lógico
// La línea de Carga indica que se va a asignar un nuevo valor al registro que viene por "entrada"
// La línea de Desplaza indica que se va a desplazar el contenido del registro. El bit más significativo se completa con la entrada "bit_en_desp"
module registro3 (input wire [2:0] entrada, input wire bit_en_desp, input wire Carga, Desplaza, clk, reset, output wire [2:0] salida);
  wire enable;
  
  assign enable = Carga | Desplaza; //Si se carga o desplaza se habilitan en modificación los biestables

  cdaff ff0(Carga, entrada[0], salida[1], clk, reset, enable, salida[0]);
  cdaff ff1(Carga, entrada[1], salida[2], clk, reset, enable, salida[1]);
  cdaff ff2(Carga, entrada[2], bit_en_desp, clk, reset, enable, salida[2]); //entra un bit en el desplaz
endmodule

//Biestable con entrada de mux para aceptar dos entradas posibles
module cdaff (input wire selc_d, inp_c, inp_d, clk, reset, carga, output wire salida);
  wire inp;
  
  ffdc ff0(clk, reset, carga, inp, salida);
  mux2_1_i1 mux0(inp, inp_d, inp_c, selc_d);
endmodule

//Mux de dos entradas de 1 bit realizado a partir de puertas 
module mux2_1_i1(output wire out, input wire a, b, s);
  //Declaración de conexiones internas
  wire  s_n, sa, sb;     
  //Instancias de puertas y sus conexiones
  not inv1 (s_n, s);
  and and1 (sa, a, s_n);
  and and2 (sb, b, s);
  or or1 (out, sa, sb);
endmodule

module ffdc #(parameter retardo = 0)(input wire clk, reset, carga, d, output reg q);
  //reset asíncrono, carga síncrona
  always @(posedge clk, posedge reset)
    if (reset)
      q <= #retardo 1'b0; //asignación no bloqueante q=0
    else
      if (carga)
        q <= #retardo d; //asignación no bloqueante q=d
endmodule

// Sumador/Restador de 4 bits
module sum_resta4(output wire[3:0] S, output wire c_out, input wire[3:0] A, input wire[3:0] B, input wire resta);
  assign {c_out, S} = (resta == 1) ? A - B + 0 : A + B + 0;
endmodule

3º/Diseno_Procesadores/Multiplicador/uc.v
module uc(input wire q0,qu, start, clk, input wire [3:0] M, A, input wire [2:0] Q, output wire CargaQ, CargaM, ResetA, CargaA, ResetQu, DesplazaA,Suma, Resta, Fin);
 reg[2:0] state, nextstate;
 
 parameter S0 = 3'b000;
 parameter S1 = 3'b001;
 parameter S2 = 3'b010;
 parameter S3 = 3'b011;
 parameter S4 = 3'b100;
 parameter S5 = 3'b101;
 parameter S6 = 3'b110;
 parameter S7 = 3'b111;
 
 always @(posedge clk, posedge start)
 if (start)
	state <= 0;
 else
	state <= nextstate;

 
 always @(*) // (*) significa cualquier cambio en alguna variable del bloque
	case (state)
		S0: nextstate = S1;
		S1: nextstate = S2;
		S2: nextstate = S3;
		S3: nextstate = S4;
		S4: nextstate = S5;
		S5: nextstate = S6;
		S6: nextstate = S7;
		S7: nextstate = S7;
		default: nextstate = S0;
	endcase
  wire en_operacion = (state==S1) | (state==S3) | (state==S5);
		
	assign ResetA = (state == S0)? 1:0;
	assign ResetQu = (state == S0)? 1:0;
	assign CargaQ = (state == S0)? 1:0;
	assign CargaM = (state == S0)? 1:0;
	assign Resta = ((q0 == 1 & qu == 0) & (state == S1 | state == S3 | state == S5))? 1:0;
	assign Suma = ((~Resta) & (state == S1 | state == S3 | state == S5))? 1:0;
	assign CargaA = en_operacion & (q0 ^ qu);   // 01 o 10
	assign DesplazaA = ((state == S2) | (state == S4) | (state == S6))? 1:0;
	assign Fin = (state == S7)? 1:0;

endmodule

3º/Diseno_Procesadores/Multiplicador/multiplicador.v
module multiplicador(input wire [3:0] multiplicando, input wire [2:0] multiplicador, input wire clk, start, output wire [5:0] resultado, output wire fin);

wire Desplaza, CargaQ, CargaM, CargaA, Resta, Suma, ResetA, ResetQ_1;
wire [3:0] A_in, A_out, M_out, suma_out;
wire [2:0] Q_out;
wire Q_1_out;
wire c_out;
uc unidadcontrol(q0, qu, start, clk, multiplicando, A_out, multiplicador, CargaQ, CargaM, ResetA, CargaA, ResetQ_1, Desplaza, Suma, Resta, fin);

registro4 A_(suma_out, A_out[3], CargaA, Desplaza, clk, ResetA, A_out);
registro4 M_(multiplicando, 1'b0, CargaM, 1'b0, clk, 1'b0, M_out);
registro3 Q_(multiplicador, A_out[0], CargaQ, Desplaza, clk, 1'b0, Q_out);

ffdc q1(clk, ResetQ_1, Desplaza, Q_out[0], Q_1_out);

sum_resta4 suma(suma_out,c_out, A_out, M_out, Resta);

// El resultado se obtiene concatenando el registro A con el registro Q
assign resultado = {A_out[2:0], Q_out};

endmodule

3º/Diseno_Procesadores/Multiplicador/multiplicador_tb.v
`timescale 1 ns / 10 ps
module multiplicador_tb;
//Recordar que el caso de -4 en tres bits en el multiplicando dará error en Booth si no hacemos que los registros A y M tengan un bit más (hay overflow) (depende de la implementación del sumador/restador)
parameter NUM_BITS = 3;
parameter NUM_TESTS = (2**(2*NUM_BITS));
parameter MAX_RANGE = (2**(NUM_BITS-1))-1;
parameter MIN_RANGE = - (2**(NUM_BITS-1));
integer contador;
reg clk, start;
wire Fin;
reg signed [NUM_BITS-1:0] multiplicador;
reg signed [NUM_BITS-1:0] multiplicando;
wire [(2*NUM_BITS)-1:0] resultado;
reg signed [(2*NUM_BITS)-1:0] resultado_esperado;

// generación de reloj clk
always //siempre activo, no hay condición de activación
begin
  clk = 1'b0;
  #5;
  clk = 1'b1;
  #5;
end

// Módulo a probar
multiplicador mult(multiplicando, multiplicador, clk, start, resultado, Fin);

initial
begin
  $dumpfile("multiplicador_tb.vcd");
  $dumpvars;
  #10000;   //Evita ejecución infinita
  $finish;
end

//Preparación caso inicial
initial
begin
  multiplicando = MIN_RANGE;
  multiplicador = MIN_RANGE;
  contador = 1;
end 

initial
begin
  start = 1'b1;
  #1;
  start = 1'b0;
end

always @(posedge Fin)
begin
  resultado_esperado = multiplicador * multiplicando;
  //Comprobación de resultados
  $write("%d x %d = %d", multiplicando, multiplicador, resultado_esperado);
  if (resultado !== resultado_esperado)
    $display("\tERROR    Obtenido=%b", resultado);
  else
    $display("\tCORRECTO Obtenido=%b", resultado);
  
  #20  //tiempo de espera entre una multiplicación y la siguiente
  if (contador == NUM_TESTS)
    $finish;
  else //Siguiente caso
  begin
    contador = contador + 1;
    if (multiplicador == MAX_RANGE)
    begin
      multiplicador = MIN_RANGE;
      multiplicando = multiplicando + 1;
    end
    else
    begin
      multiplicador = multiplicador + 1;
    end
    start = 1'b1;
    #1;
    start = 1'b0;           
  end
end

endmodule

3º/Diseno_Procesadores/Multiplicador/multiplicador_tb.vcd
$date
	Thu Feb 05 17:46:19 2026
$end
$version
	Icarus Verilog
$end
$timescale
	10ps
$end
$scope module multiplicador_tb $end
$var wire 6 ! resultado [5:0] $end
$var wire 1 " Fin $end
$var parameter 33 # MAX_RANGE $end
$var parameter 32 $ MIN_RANGE $end
$var parameter 32 % NUM_BITS $end
$var parameter 32 & NUM_TESTS $end
$var reg 1 ' clk $end
$var reg 3 ( multiplicador [2:0] $end
$var reg 3 ) multiplicando [2:0] $end
$var reg 6 * resultado_esperado [5:0] $end
$var reg 1 + start $end
$var integer 32 , contador [31:0] $end
$scope module mult $end
$var wire 1 ' clk $end
$var wire 3 - multiplicador [2:0] $end
$var wire 4 . multiplicando [3:0] $end
$var wire 1 / q0 $end
$var wire 1 0 qu $end
$var wire 1 + start $end
$var wire 4 1 suma_out [3:0] $end
$var wire 6 2 resultado [5:0] $end
$var wire 1 " fin $end
$var wire 1 3 c_out $end
$var wire 1 4 Suma $end
$var wire 1 5 Resta $end
$var wire 1 6 ResetQ_1 $end
$var wire 1 7 ResetA $end
$var wire 3 8 Q_out [2:0] $end
$var wire 1 9 Q_1_out $end
$var wire 4 : M_out [3:0] $end
$var wire 1 ; Desplaza $end
$var wire 1 < CargaQ $end
$var wire 1 = CargaM $end
$var wire 1 > CargaA $end
$var wire 4 ? A_out [3:0] $end
$scope module A_ $end
$var wire 1 @ bit_en_desp $end
$var wire 1 ' clk $end
$var wire 1 A enable $end
$var wire 4 B salida [3:0] $end
$var wire 1 7 reset $end
$var wire 4 C entrada [3:0] $end
$var wire 1 ; Desplaza $end
$var wire 1 > Carga $end
$scope module ff0 $end
$var wire 1 A carga $end
$var wire 1 ' clk $end
$var wire 1 D inp_c $end
$var wire 1 E inp_d $end
$var wire 1 > selc_d $end
$var wire 1 F salida $end
$var wire 1 7 reset $end
$var wire 1 G inp $end
$scope module ff0 $end
$var wire 1 A carga $end
$var wire 1 ' clk $end
$var wire 1 7 reset $end
$var wire 1 G d $end
$var parameter 32 H retardo $end
$var reg 1 F q $end
$upscope $end
$scope module mux0 $end
$var wire 1 E a $end
$var wire 1 D b $end
$var wire 1 G out $end
$var wire 1 I s_n $end
$var wire 1 J sa $end
$var wire 1 K sb $end
$var wire 1 > s $end
$upscope $end
$upscope $end
$scope module ff1 $end
$var wire 1 A carga $end
$var wire 1 ' clk $end
$var wire 1 L inp_c $end
$var wire 1 M inp_d $end
$var wire 1 > selc_d $end
$var wire 1 N salida $end
$var wire 1 7 reset $end
$var wire 1 O inp $end
$scope module ff0 $end
$var wire 1 A carga $end
$var wire 1 ' clk $end
$var wire 1 7 reset $end
$var wire 1 O d $end
$var parameter 32 P retardo $end
$var reg 1 N q $end
$upscope $end
$scope module mux0 $end
$var wire 1 M a $end
$var wire 1 L b $end
$var wire 1 O out $end
$var wire 1 Q s_n $end
$var wire 1 R sa $end
$var wire 1 S sb $end
$var wire 1 > s $end
$upscope $end
$upscope $end
$scope module ff2 $end
$var wire 1 A carga $end
$var wire 1 ' clk $end
$var wire 1 T inp_c $end
$var wire 1 U inp_d $end
$var wire 1 > selc_d $end
$var wire 1 V salida $end
$var wire 1 7 reset $end
$var wire 1 W inp $end
$scope module ff0 $end
$var wire 1 A carga $end
$var wire 1 ' clk $end
$var wire 1 7 reset $end
$var wire 1 W d $end
$var parameter 32 X retardo $end
$var reg 1 V q $end
$upscope $end
$scope module mux0 $end
$var wire 1 U a $end
$var wire 1 T b $end
$var wire 1 W out $end
$var wire 1 Y s_n $end
$var wire 1 Z sa $end
$var wire 1 [ sb $end
$var wire 1 > s $end
$upscope $end
$upscope $end
$scope module ff3 $end
$var wire 1 A carga $end
$var wire 1 ' clk $end
$var wire 1 \ inp_c $end
$var wire 1 @ inp_d $end
$var wire 1 > selc_d $end
$var wire 1 ] salida $end
$var wire 1 7 reset $end
$var wire 1 ^ inp $end
$scope module ff0 $end
$var wire 1 A carga $end
$var wire 1 ' clk $end
$var wire 1 7 reset $end
$var wire 1 ^ d $end
$var parameter 32 _ retardo $end
$var reg 1 ] q $end
$upscope $end
$scope module mux0 $end
$var wire 1 @ a $end
$var wire 1 \ b $end
$var wire 1 ^ out $end
$var wire 1 ` s_n $end
$var wire 1 a sa $end
$var wire 1 b sb $end
$var wire 1 > s $end
$upscope $end
$upscope $end
$upscope $end
$scope module M_ $end
$var wire 1 c Desplaza $end
$var wire 1 d bit_en_desp $end
$var wire 1 ' clk $end
$var wire 1 e enable $end
$var wire 4 f entrada [3:0] $end
$var wire 1 g reset $end
$var wire 4 h salida [3:0] $end
$var wire 1 = Carga $end
$scope module ff0 $end
$var wire 1 e carga $end
$var wire 1 ' clk $end
$var wire 1 i inp_c $end
$var wire 1 j inp_d $end
$var wire 1 g reset $end
$var wire 1 = selc_d $end
$var wire 1 k salida $end
$var wire 1 l inp $end
$scope module ff0 $end
$var wire 1 e carga $end
$var wire 1 ' clk $end
$var wire 1 g reset $end
$var wire 1 l d $end
$var parameter 32 m retardo $end
$var reg 1 k q $end
$upscope $end
$scope module mux0 $end
$var wire 1 j a $end
$var wire 1 i b $end
$var wire 1 l out $end
$var wire 1 n s_n $end
$var wire 1 o sa $end
$var wire 1 p sb $end
$var wire 1 = s $end
$upscope $end
$upscope $end
$scope module ff1 $end
$var wire 1 e carga $end
$var wire 1 ' clk $end
$var wire 1 q inp_c $end
$var wire 1 r inp_d $end
$var wire 1 g reset $end
$var wire 1 = selc_d $end
$var wire 1 s salida $end
$var wire 1 t inp $end
$scope module ff0 $end
$var wire 1 e carga $end
$var wire 1 ' clk $end
$var wire 1 g reset $end
$var wire 1 t d $end
$var parameter 32 u retardo $end
$var reg 1 s q $end
$upscope $end
$scope module mux0 $end
$var wire 1 r a $end
$var wire 1 q b $end
$var wire 1 t out $end
$var wire 1 v s_n $end
$var wire 1 w sa $end
$var wire 1 x sb $end
$var wire 1 = s $end
$upscope $end
$upscope $end
$scope module ff2 $end
$var wire 1 e carga $end
$var wire 1 ' clk $end
$var wire 1 y inp_c $end
$var wire 1 z inp_d $end
$var wire 1 g reset $end
$var wire 1 = selc_d $end
$var wire 1 { salida $end
$var wire 1 | inp $end
$scope module ff0 $end
$var wire 1 e carga $end
$var wire 1 ' clk $end
$var wire 1 g reset $end
$var wire 1 | d $end
$var parameter 32 } retardo $end
$var reg 1 { q $end
$upscope $end
$scope module mux0 $end
$var wire 1 z a $end
$var wire 1 y b $end
$var wire 1 | out $end
$var wire 1 ~ s_n $end
$var wire 1 !" sa $end
$var wire 1 "" sb $end
$var wire 1 = s $end
$upscope $end
$upscope $end
$scope module ff3 $end
$var wire 1 e carga $end
$var wire 1 ' clk $end
$var wire 1 #" inp_c $end
$var wire 1 d inp_d $end
$var wire 1 g reset $end
$var wire 1 = selc_d $end
$var wire 1 $" salida $end
$var wire 1 %" inp $end
$scope module ff0 $end
$var wire 1 e carga $end
$var wire 1 ' clk $end
$var wire 1 g reset $end
$var wire 1 %" d $end
$var parameter 32 &" retardo $end
$var reg 1 $" q $end
$upscope $end
$scope module mux0 $end
$var wire 1 d a $end
$var wire 1 #" b $end
$var wire 1 %" out $end
$var wire 1 '" s_n $end
$var wire 1 (" sa $end
$var wire 1 )" sb $end
$var wire 1 = s $end
$upscope $end
$upscope $end
$upscope $end
$scope module Q_ $end
$var wire 1 *" bit_en_desp $end
$var wire 1 ' clk $end
$var wire 1 +" enable $end
$var wire 3 ," entrada [2:0] $end
$var wire 1 -" reset $end
$var wire 3 ." salida [2:0] $end
$var wire 1 ; Desplaza $end
$var wire 1 < Carga $end
$scope module ff0 $end
$var wire 1 +" carga $end
$var wire 1 ' clk $end
$var wire 1 /" inp_c $end
$var wire 1 0" inp_d $end
$var wire 1 -" reset $end
$var wire 1 < selc_d $end
$var wire 1 1" salida $end
$var wire 1 2" inp $end
$scope module ff0 $end
$var wire 1 +" carga $end
$var wire 1 ' clk $end
$var wire 1 -" reset $end
$var wire 1 2" d $end
$var parameter 32 3" retardo $end
$var reg 1 1" q $end
$upscope $end
$scope module mux0 $end
$var wire 1 0" a $end
$var wire 1 /" b $end
$var wire 1 2" out $end
$var wire 1 4" s_n $end
$var wire 1 5" sa $end
$var wire 1 6" sb $end
$var wire 1 < s $end
$upscope $end
$upscope $end
$scope module ff1 $end
$var wire 1 +" carga $end
$var wire 1 ' clk $end
$var wire 1 7" inp_c $end
$var wire 1 8" inp_d $end
$var wire 1 -" reset $end
$var wire 1 < selc_d $end
$var wire 1 9" salida $end
$var wire 1 :" inp $end
$scope module ff0 $end
$var wire 1 +" carga $end
$var wire 1 ' clk $end
$var wire 1 -" reset $end
$var wire 1 :" d $end
$var parameter 32 ;" retardo $end
$var reg 1 9" q $end
$upscope $end
$scope module mux0 $end
$var wire 1 8" a $end
$var wire 1 7" b $end
$var wire 1 :" out $end
$var wire 1 <" s_n $end
$var wire 1 =" sa $end
$var wire 1 >" sb $end
$var wire 1 < s $end
$upscope $end
$upscope $end
$scope module ff2 $end
$var wire 1 +" carga $end
$var wire 1 ' clk $end
$var wire 1 ?" inp_c $end
$var wire 1 *" inp_d $end
$var wire 1 -" reset $end
$var wire 1 < selc_d $end
$var wire 1 @" salida $end
$var wire 1 A" inp $end
$scope module ff0 $end
$var wire 1 +" carga $end
$var wire 1 ' clk $end
$var wire 1 -" reset $end
$var wire 1 A" d $end
$var parameter 32 B" retardo $end
$var reg 1 @" q $end
$upscope $end
$scope module mux0 $end
$var wire 1 *" a $end
$var wire 1 ?" b $end
$var wire 1 A" out $end
$var wire 1 C" s_n $end
$var wire 1 D" sa $end
$var wire 1 E" sb $end
$var wire 1 < s $end
$upscope $end
$upscope $end
$upscope $end
$scope module q1 $end
$var wire 1 ' clk $end
$var wire 1 F" d $end
$var wire 1 6 reset $end
$var wire 1 ; carga $end
$var parameter 32 G" retardo $end
$var reg 1 9 q $end
$upscope $end
$scope module suma $end
$var wire 4 H" A [3:0] $end
$var wire 4 I" B [3:0] $end
$var wire 1 5 resta $end
$var wire 1 3 c_out $end
$var wire 4 J" S [3:0] $end
$upscope $end
$scope module unidadcontrol $end
$var wire 4 K" A [3:0] $end
$var wire 1 > CargaA $end
$var wire 4 L" M [3:0] $end
$var wire 3 M" Q [2:0] $end
$var wire 1 ' clk $end
$var wire 1 N" en_operacion $end
$var wire 1 / q0 $end
$var wire 1 0 qu $end
$var wire 1 + start $end
$var wire 1 4 Suma $end
$var wire 1 5 Resta $end
$var wire 1 6 ResetQu $end
$var wire 1 7 ResetA $end
$var wire 1 " Fin $end
$var wire 1 ; DesplazaA $end
$var wire 1 < CargaQ $end
$var wire 1 = CargaM $end
$var parameter 3 O" S0 $end
$var parameter 3 P" S1 $end
$var parameter 3 Q" S2 $end
$var parameter 3 R" S3 $end
$var parameter 3 S" S4 $end
$var parameter 3 T" S5 $end
$var parameter 3 U" S6 $end
$var parameter 3 V" S7 $end
$var reg 3 W" nextstate [2:0] $end
$var reg 3 X" state [2:0] $end
$upscope $end
$upscope $end
$upscope $end
$enddefinitions $end
$comment Show the parameter values. $end
$dumpall
b111 V"
b110 U"
b101 T"
b100 S"
b11 R"
b10 Q"
b1 P"
b0 O"
b0 G"
b0 B"
b0 ;"
b0 3"
b0 &"
b0 }
b0 u
b0 m
b0 _
b0 X
b0 P
b0 H
b1000000 &
b11 %
b11111111111111111111111111111100 $
b11 #
$end
#0
$dumpvars
b0 X"
b1 W"
0N"
b100 M"
b1100 L"
b0 K"
bx J"
bx I"
b0 H"
xF"
1E"
0D"
0C"
1A"
x@"
1?"
0>"
0="
0<"
0:"
x9"
x8"
07"
06"
05"
04"
02"
x1"
x0"
0/"
bx ."
0-"
b100 ,"
1+"
0*"
1)"
0("
0'"
1%"
x$"
1#"
1""
0!"
0~
1|
x{
xz
1y
0x
0w
0v
0t
xs
xr
0q
0p
0o
0n
0l
xk
xj
0i
bx h
0g
b1100 f
1e
0d
0c
0b
0a
1`
0^
0]
x\
0[
0Z
1Y
0W
0V
0U
xT
0S
0R
1Q
0O
0N
0M
xL
0K
0J
1I
0G
0F
0E
xD
bx C
b0 B
0A
0@
b0 ?
0>
1=
1<
0;
bx :
09
bx 8
17
16
05
04
x3
b0xxx 2
bx 1
z0
z/
b1100 .
b100 -
b1 ,
1+
bx *
b100 )
b100 (
0'
0"
b0xxx !
$end
#100
0+
#500
x^
xW
1:"
1t
x5
x4
xb
x`
x[
xY
xQ
xI
xA
0A"
1="
0%"
1!"
1w
x\
1T
0L
0D
x>
0E"
1C"
1<"
14"
0+"
0)"
1'"
0""
1~
1v
1n
0e
bx100 1
bx100 C
bx100 J"
x3
1N"
07
06
0<
0=
0j
1r
1z
0F"
00"
18"
b10 W"
0k
0s
1{
b1100 :
b1100 h
b1100 I"
1$"
01"
09"
b100 !
b100 2
b100 8
b100 ."
1@"
b1 X"
1'
#1000
0'
#1500
1\
b1100 1
b1100 C
b1100 J"
03
0^
0W
05
04
1+"
0b
1`
0[
1Y
1Q
1I
1A
1;
0>
0N"
b11 W"
b10 X"
1'
#2000
0'
#2500
x\
bx100 1
bx100 C
bx100 J"
x3
x^
xW
x5
x4
0+"
xb
x`
x[
xY
xQ
xI
xA
0;
12"
0:"
x>
15"
0="
1N"
10"
08"
b100 W"
19"
b10 !
b10 2
b10 8
b10 ."
0@"
b11 X"
1'
#3000
0'
#3500
1\
b1100 1
b1100 C
b1100 J"
03
0^
0W
05
04
1+"
0b
1`
0[
1Y
1Q
1I
1A
1;
0>
0N"
b101 W"
b100 X"
1'
#4000
0'
#4500
x\
bx100 1
bx100 C
bx100 J"
x3
0+"
xA
x^
xW
x5
x4
0;
02"
xb
x`
x[
xY
xQ
xI
05"
x>
1F"
00"
b110 W"
1N"
11"
b1 !
b1 2
b1 8
b1 ."
09"
b101 X"
1'
#5000
0'
#5500
1\
b1100 1
b1100 C
b1100 J"
03
0^
0W
05
04
1+"
0b
1`
0[
1Y
1Q
1I
1A
1;
0>
b111 W"
0N"
b110 X"
1'
#6000
0'
#6500
0+"
0A
0;
b10000 *
1"
0F"
b0 !
b0 2
b0 8
b0 ."
01"
19
b111 X"
1'
#7000
0'
#7500
1'
#8000
0'
#8500
09
0t
1A"
12"
1%"
0!"
0w
1E"
0C"
0<"
16"
04"
1+"
1)"
0'"
1""
0~
0v
0n
1e
17
16
1<
1=
0"
b1 W"
b0 X"
1/"
1'
1+
b101 (
b101 -
b101 ,"
b101 M"
b10 ,
#8600
0+
#9000
0'
#9500
x\
bx100 1
bx100 C
bx100 J"
x3
x^
xW
1:"
1t
x5
x4
xb
x`
x[
xY
xQ
xI
xA
0A"
1="
02"
0%"
1!"
1w
x>
0E"
1C"
1<"
06"
14"
0+"
0)"
1'"
0""
1~
1v
1n
0e
1N"
07
06
0<
0=
18"
1F"
b10 W"
1@"
b101 !
b101 2
b101 8
b101 ."
11"
b1 X"
1'
#10000
0'
#10500
1\
b1100 1
b1100 C
b1100 J"
03
0^
0W
05
04
1+"
0b
1`
0[
1Y
1Q
1I
1A
1;
0>
0N"
b11 W"
b10 X"
1'
#11000
0'
#11500
x\
bx100 1
bx100 C
bx100 J"
x3
x^
xW
x5
x4
0+"
xb
x`
x[
xY
xQ
xI
xA
0;
0:"
12"
x>
0="
15"
1N"
08"
10"
0F"
b100 W"
0@"
19"
b10 !
b10 2
b10 8
b10 ."
01"
19
b11 X"
1'
#12000
0'
#12500
1\
b1100 1
b1100 C
b1100 J"
03
0^
0W
05
04
1+"
0b
1`
0[
1Y
1Q
1I
1A
1;
0>
0N"
b101 W"
b100 X"
1'
#13000
0'
#13500
x\
bx100 1
bx100 C
bx100 J"
x3
0+"
xA
x^
xW
x5
x4
0;
02"
xb
x`
x[
xY
xQ
xI
05"
x>
00"
1F"
b110 W"
1N"
09"
b1 !
b1 2
b1 8
b1 ."
11"
09
b101 X"
1'
#14000
0'
#14500
1\
b1100 1
b1100 C
b1100 J"
03
0^
0W
05
04
1+"
0b
1`
0[
1Y
1Q
1I
1A
1;
0>
b111 W"
0N"
b110 X"
1'
#15000
0'
#15500
0+"
0A
0;
b1100 *
1"
0F"
b0 !
b0 2
b0 8
b0 ."
01"
19
b111 X"
1'
#16000
0'
#16500
1'
#17000
0'
#17500
09
0t
1A"
1:"
1%"
0!"
0w
1E"
0C"
1>"
0<"
04"
1+"
1)"
0'"
1""
0~
0v
0n
1e
17
16
1<
1=
0"
b1 W"
b0 X"
0/"
17"
1'
1+
b110 (
b110 -
b110 ,"
b110 M"
b11 ,
#17600
0+
#18000
0'
#18500
x\
bx100 1
bx100 C
bx100 J"
x3
x^
xW
12"
1t
x5
x4
xb
x`
x[
xY
xQ
xI
xA
0A"
1="
15"
0%"
1!"
1w
x>
0E"
1C"
0>"
1<"
14"
0+"
0)"
1'"
0""
1~
1v
1n
0e
1N"
07
06
0<
0=
10"
18"
b10 W"
19"
b110 !
b110 2
b110 8
b110 ."
1@"
b1 X"
1'
#19000
0'
#19500
1\
b1100 1
b1100 C
b1100 J"
03
0^
0W
05
04
1+"
0b
1`
0[
1Y
1Q
1I
1A
1;
0>
0N"
b11 W"
b10 X"
1'
#20000
0'
#20500
x\
bx100 1
bx100 C
bx100 J"
x3
x^
xW
x5
x4
0+"
xb
x`
x[
xY
xQ
xI
xA
0;
0:"
x>
0="
1N"
1F"
08"
b100 W"
11"
b11 !
b11 2
b11 8
b11 ."
0@"
b11 X"
1'
#21000
0'
#21500
1\
b1100 1
b1100 C
b1100 J"
03
0^
0W
05
04
1+"
0b
1`
0[
1Y
1Q
1I
1A
1;
0>
0N"
b101 W"
b100 X"
1'
#22000
0'
#22500
x\
bx100 1
bx100 C
bx100 J"
x3
0+"
xA
x^
xW
x5
x4
0;
02"
xb
x`
x[
xY
xQ
xI
05"
x>
00"
b110 W"
1N"
b1 !
b1 2
b1 8
b1 ."
09"
19
b101 X"
1'
#23000
0'
#23500
1\
b1100 1
b1100 C
b1100 J"
03
0^
0W
05
04
1+"
0b
1`
0[
1Y
1Q
1I
1A
1;
0>
b111 W"
0N"
b110 X"
1'
#24000
0'
#24500
0+"
0A
0;
b1000 *
1"
0F"
b0 !
b0 2
b0 8
b0 ."
01"
b111 X"
1'
#25000
0'
#25500
1'
#26000
0'
#26500
09
0t
1A"
1:"
12"
1%"
0!"
0w
1E"
0C"
1>"
0<"
16"
04"
1+"
1)"
0'"
1""
0~
0v
0n
1e
17
16
1<
1=
0"
b1 W"
b0 X"
1/"
1'
1+
b111 (
b111 -
b111 ,"
b111 M"
b100 ,
#26600
0+
#27000
0'
#27500
x\
bx100 1
bx100 C
bx100 J"
x3
x^
xW
1t
x5
x4
xb
x`
x[
xY
xQ
xI
xA
0A"
1="
15"
0%"
1!"
1w
x>
0E"
1C"
0>"
1<"
06"
14"
0+"
0)"
1'"
0""
1~
1v
1n
0e
1N"
07
06
0<
0=
18"
10"
1F"
b10 W"
1@"
19"
b111 !
b111 2
b111 8
b111 ."
11"
b1 X"
1'
#28000
0'
#28500
1\
b1100 1
b1100 C
b1100 J"
03
0^
0W
05
04
1+"
0b
1`
0[
1Y
1Q
1I
1A
1;
0>
0N"
b11 W"
b10 X"
1'
#29000
0'
#29500
x\
bx100 1
bx100 C
bx100 J"
x3
x^
xW
x5
x4
0+"
xb
x`
x[
xY
xQ
xI
xA
0;
0:"
x>
0="
1N"
08"
b100 W"
b11 !
b11 2
b11 8
b11 ."
0@"
19
b11 X"
1'
#30000
0'
#30500
1\
b1100 1
b1100 C
b1100 J"
03
0^
0W
05
04
1+"
0b
1`
0[
1Y
1Q
1I
1A
1;
0>
0N"
b101 W"
b100 X"
1'
#31000
0'
#31500
x\
bx100 1
bx100 C
bx100 J"
x3
0+"
xA
x^
xW
x5
x4
0;
02"
xb
x`
x[
xY
xQ
xI
05"
x>
00"
b110 W"
1N"
b1 !
b1 2
b1 8
b1 ."
09"
b101 X"
1'
#32000
0'
#32500
1\
b1100 1
b1100 C
b1100 J"
03
0^
0W
05
04
1+"
0b
1`
0[
1Y
1Q
1I
1A
1;
0>
b111 W"
0N"
b110 X"
1'
#33000
0'
#33500
0+"
0A
0;
b100 *
1"
0F"
b0 !
b0 2
b0 8
b0 ."
01"
b111 X"
1'
#34000
0'
#34500
1'
#35000
0'
#35500
09
0t
1%"
0!"
0w
0C"
0<"
04"
1+"
1)"
0'"
1""
0~
0v
0n
1e
17
16
1<
1=
0"
b1 W"
b0 X"
0/"
07"
0?"
1'
1+
b0 (
b0 -
b0 ,"
b0 M"
b101 ,
#35600
0+
#36000
0'
#36500
x\
bx100 1
bx100 C
bx100 J"
x3
x^
xW
1t
x5
x4
xb
x`
x[
xY
xQ
xI
xA
0%"
1!"
1w
x>
1C"
1<"
14"
0+"
0)"
1'"
0""
1~
1v
1n
0e
1N"
07
06
0<
0=
b10 W"
b1 X"
1'
#37000
0'
#37500
1\
b1100 1
b1100 C
b1100 J"
03
0^
0W
05
04
1+"
0b
1`
0[
1Y
1Q
1I
1A
1;
0>
0N"
b11 W"
b10 X"
1'
#38000
0'
#38500
x\
bx100 1
bx100 C
bx100 J"
x3
x^
xW
x5
x4
0+"
xb
x`
x[
xY
xQ
xI
xA
0;
x>
1N"
b100 W"
b11 X"
1'
#39000
0'
#39500
1\
b1100 1
b1100 C
b1100 J"
03
0^
0W
05
04
1+"
0b
1`
0[
1Y
1Q
1I
1A
1;
0>
0N"
b101 W"
b100 X"
1'
#40000
0'
#40500
x\
bx100 1
bx100 C
bx100 J"
x3
0+"
xA
x^
xW
x5
x4
0;
xb
x`
x[
xY
xQ
xI
x>
b110 W"
1N"
b101 X"
1'
#41000
0'
#41500
1\
b1100 1
b1100 C
b1100 J"
03
0^
0W
05
04
1+"
0b
1`
0[
1Y
1Q
1I
1A
1;
0>
b111 W"
0N"
b110 X"
1'
#42000
0'
#42500
0+"
0A
0;
b0 *
1"
b111 X"
1'
#43000
0'
#43500
1'
#44000
0'
#44500
0t
12"
1%"
0!"
0w
0C"
0<"
16"
04"
1+"
1)"
0'"
1""
0~
0v
0n
1e
17
16
1<
1=
0"
b1 W"
b0 X"
1/"
1'
1+
b1 (
b1 -
b1 ,"
b1 M"
b110 ,
#44600
0+
#45000
0'
