2º/Estructura_de_Computadores/Practica_01_modificacion/fa.v
//Declaración del módulo del Sumador completo
module fa(output wire c_out, sum, input wire a, b, c_in);
// Asignación continua de c_out y sum dado por la suma de a + b + c_in.
assign {c_out,sum} = a + b + c_in;

endmodule

Estructura_de_Computadores/Practica_01/mux2_4.v
//Multiplexor 2 a 1.
module mux2_4(output wire [3:0] Out, input wire [3:0] A, input wire [3:0] B, input wire s);
//Asignación a Out dependiendo del valor de s para obtener B o A.
assign Out = (s)?B:A;
endmodule

2/Estructura_de_Computadores/Practica_01_modificacion/mux4_1.v
//Multiplexor 4 a 1
module mux4_1(output reg out, input wire a, b, c, d, input wire [1:0] S);

 always@(a,b,c,d,S)
 begin
  case(S)
    2'b00: out = a;
    2'b01: out = b;
    2'b10: out = c;
    2'b11: out = d;
  endcase
 end
endmodule

2/Estructura_de_Computadores/Practica_01_modificacion/cl.v
// Declaración del módulo de la Celda lógica
module cl(output wire out, input wire a, b, input wire [1:0] S);
// Declaramos los wire para que los operadores lógicos tengan una salida
wire wire1,wire2,wire3,wire4;
// Creación de operador lógico and
and and1(wire1 ,a, b);
// Creación de operador lógico or
or or1(wire2, a, b);
// Creación de operador lógico xor
xor xor1(wire3, a, b);
// Creación de operador lógico not
not not1(wire4,b);
// Implementamos el multiplexor 4 a 1 con los wire
mux4_1 mux4_1_1(out, wire1, wire2, wire3, wire4,S);

endmodule

2/Estructura_de_Computadores/Practica_01_modificacion/ul4.v
// Unidad lógica de 4 bits
module ul4(output wire[3:0] Out, input wire[3:0] A, input wire[3:0] B, input wire [1:0] S);
  //Primera celda lógica
  cl cl1(Out[0],A[0],B[0],S);
  //Segunda celda lógica
  cl cl2(Out[1],A[1],B[1],S);
  //Tercera celda lógica
  cl cl3(Out[2],A[2],B[2],S);
  //Cuarta celda lógica
  cl cl4(Out[3],A[3],B[3],S);

endmodule

2/Estructura_de_Computadores/Practica_01/sum4.v
//Sumador completo de tipo estructural
module sum4(output wire[3:0] S, output wire c_out, input wire[3:0] A, input wire[3:0] B, input wire c_in);
// Declaración de los wire
wire C1,C2,C3;
// Sumador completo del primer bit
fa fa1(C1,S[0],A[0],B[0],c_in);
// Sumador completo del segundo bit
fa fa2(C2,S[1],A[1],B[1],C1);
// Sumador completo del tercer bit
fa fa3(C3,S[2],A[2],B[2],C2);
// Sumador completo del cuarto bit
fa fa4(c_out,S[3],A[3],B[3],C3);

endmodule

Estructura_de_Computadores/ficheros_previa_P1/control.v
module control(output wire add1, op1_A, op_B,cpl, input wire [2:0])

endmodule

Estructura_de_Computadores/Practica_01_modificacion/cpl1.v
// Declaración del módulo de complemento a 1.
module cpl1(output wire [3:0] Out, input wire [3:0] Inp, input wire cpl);
/* Asignación continua de Out dependiendo si cpl es 1 o 0 para que se invierta o no 
los bits de Inp.*/
assign Out = (cpl == 1)? ~Inp : Inp;

endmodule

Estructura_de_Computadores/Practica_01_modificacion/preprocess.v
module preprocess(output wire [3:0] AMod, output wire [3:0] BMod, input wire [3:0] A,
input wire [3:0] B, input wire [2:0] Op);
// Declaración de los wire de 1 bit
wire add1,op1_A,op2_B,cpl;
// Declaración de los wire de 4 bits
wire[3:0] wiremux1, wiremux2;
/*Llamada al multiplexor 2 a 1 de 4 bits
IN: 0 ,1; OUT: wiremux1; señal de control: add1 
*/
mux2_4 mux2_1(wiremux1,4'b0000,4'b0001,add1);
/*Llamada al multiplexor 2 a 1 de 4 bits
IN: A, B; OUT: wiremux2; señal de control: op2_B 
*/
mux2_4 mux2_2(wiremux2,A,B,op2_B);
/*Llamada al multiplexor 2 a 1 de 4 bits
IN: A , wiremux1; OUT: AMod; señal de control: op1_A 
*/
mux2_4 mux2_3(AMod,wiremux1,A,op1_A);
/*Llamada al complementario a 1.
IN: wiremux2; OUT: BMod; señal de control: cpl
*/
cpl1   cpl_1(BMod,wiremux2,cpl);
/*Llamada al modulo de control
IN: Op ; OUT: add1, op1_A, op2_B, cpl
*/
control control_1(add1, op1_A, op2_B, cpl, Op);

endmodule

Estructura_de_Computadores/Practica_01_modificacion/alu.v
// Declaración del módulo alu
module alu(output wire [3:0] R, output wire zero, carry, sign, input wire [3:0] A, B, input wire c_in,
input wire [2:0] Op);
// Declaración los wire de 4 bits.
wire[3:0] OP1,OP2,sum4_wire,ul4_wire;
//Llamada al módulo preprocess.
preprocess preprocess_1(OP1,OP2,A,B,Op);
//Llamada al módulo sum4(sumador de 4 bits).
sum4 sum4_1(sum4_wire,carry,OP1,OP2,c_in);
//Llamada al módulo ul(unidad lógica).
ul4  ul4_1(ul4_wire,OP1,OP2,Op[1:0]);
//Llamada al módulo mux2_4(Multiplexor 2 a 1 de 4 bits).
mux2_4 mux2_4_1(R,sum4_wire,ul4_wire,Op[2]);
//Asignación zero a 1 si R == 0.
assign zero = (R == 4'b0000);
//Asignación sign al primer bit de R.
assign sign = (R[3]);

endmodule

Estructura_de_Computadores/Practica_01_modificacion/alu_tb_modPE104.v
// Testbench para modulo alu
`timescale 1 ns / 10 ps //Directiva que fija la unidad de tiempo de simulación y la precision de la unidad
module alu_tb;
//declaracion de señales
reg [2:0] t_Op;
reg t_cin;
reg [3:0] t_A, t_B; 
wire [3:0] t_R;
wire t_z, t_c, t_s;
integer errores;

// error de cualquier tipo, de resultado, de linea zero, de signo y carry
reg error, error_R, error_z, error_s, error_c; 

//instancia del modulo a testear
alu mat(t_R, t_z, t_c, t_s, t_A, t_B, t_cin, t_Op);


initial
begin
	$dumpfile("alu_mod.vcd");
	$dumpvars;

	errores = 0;
	
	t_Op = 3'b000;
	repeat(8)
	begin
		t_cin = 1'b0;
		repeat(2)
		begin
			t_A = 4'b0;
			repeat(16) 
			begin
				t_B = 4'b0;
				repeat(16) 
				begin
					#0.01 check;
					#9.99;
					t_B = t_B + 1;
				end
				t_A = t_A + 1;
			end
			t_cin = t_cin + 1;
		end
		t_Op = t_Op + 1;
	end
	$display("Encontradas %d operaciones erroneas", errores);
  	//fin simulacion
  	$finish;
end

// Tarea para hacer la comprobación automática de resultados
task check;
reg [4:0] expected_R;
reg expected_z, expected_c, expected_s;

begin
	$write("tiempo=%0d A=%b B=%b c_in=%b OP=%b R=%b, Z=%b, C=%b, S=%b.", $time, t_A, t_B, t_cin, t_Op, t_R, t_z, t_c, t_s);
	case (t_Op)	
		3'b000: expected_R = (t_A ^4'b1111) + 4'b0001 + t_cin;
		3'b001: expected_R = t_A + t_cin;
		3'b010: expected_R = t_A + t_B + t_cin;
		3'b011: expected_R = t_A + 1 + t_cin;
		3'b100: expected_R = t_A & t_B;
		3'b101: expected_R = t_A | t_B;
		3'b110: expected_R = t_A ^ t_B;
		3'b111: expected_R[3:0] = ~t_A;
		default: $display("ERROR. Valor no esperado para t_Op: %b", t_Op);
	endcase
	if (t_Op[2]) // Si la operación es lógica
	begin
		expected_c = 1'b0;
		expected_s = expected_R[3];
		error_s = 0;
	 	error_c = 0;
	end
	else
	begin
		expected_c = expected_R[4];
		expected_s = expected_R[3];
		error_s = (expected_s !== t_s);
	 	error_c = (expected_c !== t_c);
	end

	expected_z = ~| expected_R[3:0];
	// generacion señales error generales para toda la ALU
	error_R = (expected_R[3:0] !== t_R); 
	error_z = (expected_z !== t_z);
	error = error_R | error_z | error_s | error_c;
	if (error)
	begin
		errores = errores + 1;
		$display(" ---- ERROR");
		if (error_R)
			$display("\tResultado esperado %b, obtenido %b", expected_R[3:0], t_R);
		if (error_z)
			$display("\tFlag de cero esperado %b, obtenido %b", expected_z, t_z);
		if (error_s)
			$display("\tFlag de signo esperado %b, obtenido %b", expected_s, t_s);
		if (error_c)
			$display("\tFlag de acarreo esperado %b, obtenido %b", expected_c, t_c);
	end
	else
		$display(" ---- OK");
end
endtask
endmodule

Estructura_de_Computadores/Practica_01_modificacion/alu.vcd
$date
	Wed Oct 16 16:37:52 2024
$end
$version
	Icarus Verilog
$end
$timescale
	10ps
$end
$scope module alu_tb $end
$var wire 1 ! t_z $end
$var wire 1 " t_s $end
$var wire 1 # t_c $end
$var wire 4 $ t_R [3:0] $end
$var reg 1 % error $end
$var reg 1 & error_R $end
$var reg 1 ' error_c $end
$var reg 1 ( error_s $end
$var reg 1 ) error_z $end
$var reg 4 * t_A [3:0] $end
$var reg 4 + t_B [3:0] $end
$var reg 3 , t_Op [2:0] $end
$var reg 1 - t_cin $end
$var integer 32 . errores [31:0] $end
$scope module mat $end
$var wire 4 / A [3:0] $end
$var wire 4 0 B [3:0] $end
$var wire 3 1 Op [2:0] $end
$var wire 1 - c_in $end
$var wire 1 ! zero $end
$var wire 4 2 ul4_wire [3:0] $end
$var wire 4 3 sum4_wire [3:0] $end
$var wire 1 " sign $end
$var wire 1 # carry $end
$var wire 4 4 R [3:0] $end
$var wire 4 5 OP2 [3:0] $end
$var wire 4 6 OP1 [3:0] $end
$scope module mux2_4_1 $end
$var wire 1 7 s $end
$var wire 4 8 Out [3:0] $end
$var wire 4 9 B [3:0] $end
$var wire 4 : A [3:0] $end
$upscope $end
$scope module preprocess_1 $end
$var wire 4 ; A [3:0] $end
$var wire 4 < B [3:0] $end
$var wire 3 = Op [2:0] $end
$var wire 1 > add1 $end
$var wire 1 ? cpl $end
$var wire 1 @ op1_A $end
$var wire 1 A op2_B $end
$var wire 4 B wiremux2 [3:0] $end
$var wire 4 C wiremux1 [3:0] $end
$var wire 4 D BMod [3:0] $end
$var wire 4 E AMod [3:0] $end
$scope module cpl_1 $end
$var wire 1 ? cpl $end
$var wire 4 F Out [3:0] $end
$var wire 4 G Inp [3:0] $end
$upscope $end
$scope module mux2_1 $end
$var wire 4 H A [3:0] $end
$var wire 4 I B [3:0] $end
$var wire 1 > s $end
$var wire 4 J Out [3:0] $end
$upscope $end
$scope module mux2_2 $end
$var wire 4 K A [3:0] $end
$var wire 4 L B [3:0] $end
$var wire 1 A s $end
$var wire 4 M Out [3:0] $end
$upscope $end
$scope module mux2_3 $end
$var wire 4 N A [3:0] $end
$var wire 4 O B [3:0] $end
$var wire 1 @ s $end
$var wire 4 P Out [3:0] $end
$upscope $end
$upscope $end
$scope module sum4_1 $end
$var wire 4 Q A [3:0] $end
$var wire 4 R B [3:0] $end
$var wire 1 - c_in $end
$var wire 1 # c_out $end
$var wire 4 S S [3:0] $end
$var wire 1 T C3 $end
$var wire 1 U C2 $end
$var wire 1 V C1 $end
$upscope $end
$scope module ul4_1 $end
$var wire 4 W A [3:0] $end
$var wire 4 X B [3:0] $end
$var wire 2 Y S [1:0] $end
$var wire 4 Z Out [3:0] $end
$scope module cl1 $end
$var wire 2 [ S [1:0] $end
$var wire 1 \ a $end
$var wire 1 ] b $end
$var wire 1 ^ wire1 $end
$var wire 1 _ wire2 $end
$var wire 1 ` wire3 $end
$var wire 1 a wire4 $end
$var wire 1 b out $end
$scope module mux4_1_1 $end
$var wire 2 c S [1:0] $end
$var wire 1 ^ a $end
$var wire 1 _ b $end
$var wire 1 ` c $end
$var wire 1 a d $end
$var reg 1 b out $end
$upscope $end
$upscope $end
$scope module cl2 $end
$var wire 2 d S [1:0] $end
$var wire 1 e a $end
$var wire 1 f b $end
$var wire 1 g wire1 $end
$var wire 1 h wire2 $end
$var wire 1 i wire3 $end
$var wire 1 j wire4 $end
$var wire 1 k out $end
$scope module mux4_1_1 $end
$var wire 2 l S [1:0] $end
$var wire 1 g a $end
$var wire 1 h b $end
$var wire 1 i c $end
$var wire 1 j d $end
$var reg 1 k out $end
$upscope $end
$upscope $end
$scope module cl3 $end
$var wire 2 m S [1:0] $end
$var wire 1 n a $end
$var wire 1 o b $end
$var wire 1 p wire1 $end
$var wire 1 q wire2 $end
$var wire 1 r wire3 $end
$var wire 1 s wire4 $end
$var wire 1 t out $end
$scope module mux4_1_1 $end
$var wire 2 u S [1:0] $end
$var wire 1 p a $end
$var wire 1 q b $end
$var wire 1 r c $end
$var wire 1 s d $end
$var reg 1 t out $end
$upscope $end
$upscope $end
$scope module cl4 $end
$var wire 2 v S [1:0] $end
$var wire 1 w a $end
$var wire 1 x b $end
$var wire 1 y wire1 $end
$var wire 1 z wire2 $end
$var wire 1 { wire3 $end
$var wire 1 | wire4 $end
$var wire 1 } out $end
$scope module mux4_1_1 $end
$var wire 2 ~ S [1:0] $end
$var wire 1 y a $end
$var wire 1 z b $end
$var wire 1 { c $end
$var wire 1 | d $end
$var reg 1 } out $end
$upscope $end
$upscope $end
$upscope $end
$upscope $end
$scope task check $end
$var reg 5 !" expected_R [4:0] $end
$var reg 1 "" expected_c $end
$var reg 1 #" expected_s $end
$var reg 1 $" expected_z $end
$upscope $end
$upscope $end
$scope module fa $end
$var wire 1 %" a $end
$var wire 1 &" b $end
$var wire 1 '" c_in $end
$var wire 1 (" sum $end
$var wire 1 )" c_out $end
$upscope $end
$enddefinitions $end
$comment Show the parameter values. $end
$dumpall
$end
#0
$dumpvars
x)"
x("
z'"
z&"
z%"
x$"
x#"
x""
bx !"
b0 ~
0}
1|
0{
0z
0y
0x
0w
b0 v
b0 u
0t
1s
0r
0q
0p
0o
0n
b0 m
b0 l
0k
1j
0i
0h
0g
0f
0e
b0 d
b0 c
0b
1a
0`
0_
0^
0]
0\
b0 [
b0 Z
b0 Y
b0 X
b0 W
0V
0U
0T
b0 S
b0 R
b0 Q
b0 P
b0 O
b0 N
b0 M
b0 L
b0 K
b0 J
b1 I
b0 H
b0 G
b0 F
b0 E
b0 D
b0 C
b0 B
0A
0@
0?
0>
b0 =
b0 <
b0 ;
b0 :
b0 9
b0 8
07
b0 6
b0 5
b0 4
b0 3
b0 2
b0 1
b0 0
b0 /
b0 .
0-
b0 ,
b0 +
b0 *
x)
x(
x'
x&
x%
b0 $
0#
0"
1!
$end
#1
0%
0)
0&
1$"
0'
0(
0#"
0""
b0 !"
#1000
b1 +
b1 0
b1 <
b1 L
#2000
b10 +
b10 0
b10 <
b10 L
#3000
b11 +
b11 0
b11 <
b11 L
#4000
b100 +
b100 0
b100 <
b100 L
#5000
b101 +
b101 0
b101 <
b101 L
#6000
b110 +
b110 0
b110 <
b110 L
#7000
b111 +
b111 0
b111 <
b111 L
#8000
b1000 +
b1000 0
b1000 <
b1000 L
#9000
b1001 +
b1001 0
b1001 <
b1001 L
#10000
b1010 +
b1010 0
b1010 <
b1010 L
#11000
b1011 +
b1011 0
b1011 <
b1011 L
#12000
b1100 +
b1100 0
b1100 <
b1100 L
#13000
b1101 +
b1101 0
b1101 <
b1101 L
#14000
b1110 +
b1110 0
b1110 <
b1110 L
#15000
b1111 +
b1111 0
b1111 <
b1111 L
#16000
0!
b1 $
b1 4
b1 8
b1 3
b1 :
b1 S
1_
1`
0a
1]
b1 5
b1 D
b1 F
b1 R
b1 X
b1 B
b1 G
b1 M
b1 *
b1 /
b1 ;
b1 K
b1 O
b0 +
b0 0
b0 <
b0 L
#16001
0$"
b1 !"
#17000
b1 +
b1 0
b1 <
b1 L
#18000
b10 +
b10 0
b10 <
b10 L
#19000
b11 +
b11 0
b11 <
b11 L
#20000
b100 +
b100 0
b100 <
b100 L
#21000
b101 +
b101 0
b101 <
b101 L
#22000
b110 +
b110 0
b110 <
b110 L
#23000
b111 +
b111 0
b111 <
b111 L
#24000
b1000 +
b1000 0
b1000 <
b1000 L
#25000
b1001 +
b1001 0
b1001 <
b1001 L
#26000
b1010 +
b1010 0
b1010 <
b1010 L
#27000
b1011 +
b1011 0
b1011 <
b1011 L
#28000
b1100 +
b1100 0
b1100 <
b1100 L
#29000
b1101 +
b1101 0
b1101 <
b1101 L
#30000
b1110 +
b1110 0
b1110 <
b1110 L
#31000
b1111 +
b1111 0
b1111 <
b1111 L
#32000
b10 $
b10 4
b10 8
b10 3
b10 :
b10 S
0_
0`
1a
1h
1i
0j
0]
1f
b10 5
b10 D
b10 F
b10 R
b10 X
b10 B
b10 G
b10 M
b10 *
b10 /
b10 ;
b10 K
b10 O
b0 +
b0 0
b0 <
b0 L
#32001
b10 !"
#33000
b1 +
b1 0
b1 <
b1 L
#34000
b10 +
b10 0
b10 <
b10 L
#35000
b11 +
b11 0
b11 <
b11 L
#36000
b100 +
b100 0
b100 <
b100 L
#37000
b101 +
b101 0
b101 <
b101 L
#38000
b110 +
b110 0
b110 <
b110 L
#39000
b111 +
b111 0
b111 <
b111 L
#40000
b1000 +
b1000 0
b1000 <
b1000 L
#41000
b1001 +
b1001 0
b1001 <
b1001 L
#42000
b1010 +
b1010 0
b1010 <
b1010 L
#43000
b1011 +
b1011 0
b1011 <
b1011 L
#44000
b1100 +
b1100 0
b1100 <
b1100 L
#45000
b1101 +
b1101 0
b1101 <
b1101 L
#46000
b1110 +
b1110 0
b1110 <
b1110 L
#47000
b1111 +
b1111 0
b1111 <
b1111 L
#48000
b11 $
b11 4
b11 8
b11 3
b11 :
b11 S
1_
1`
0a
1]
b11 5
b11 D
b11 F
b11 R
b11 X
b11 B
b11 G
b11 M
b11 *
b11 /
b11 ;
b11 K
b11 O
b0 +
b0 0
b0 <
b0 L
#48001
b11 !"
#49000
b1 +
b1 0
b1 <
b1 L
#50000
b10 +
b10 0
b10 <
b10 L
#51000
b11 +
b11 0
b11 <
b11 L
#52000
b100 +
b100 0
b100 <
b100 L
#53000
b101 +
b101 0
b101 <
b101 L
#54000
b110 +
b110 0
b110 <
b110 L
#55000
b111 +
b111 0
b111 <
b111 L
#56000
b1000 +
b1000 0
b1000 <
b1000 L
#57000
b1001 +
b1001 0
b1001 <
b1001 L
#58000
b1010 +
b1010 0
b1010 <
b1010 L
#59000
b1011 +
b1011 0
b1011 <
b1011 L
#60000
b1100 +
b1100 0
b1100 <
b1100 L
#61000
b1101 +
b1101 0
b1101 <
b1101 L
#62000
b1110 +
b1110 0
b1110 <
b1110 L
#63000
b1111 +
b1111 0
b1111 <
b1111 L
#64000
b100 $
b100 4
b100 8
b100 3
b100 :
b100 S
0_
0`
1a
0h
0i
1j
1q
1r
0s
0]
0f
1o
b100 5
b100 D
b100 F
b100 R
b100 X
b100 B
b100 G
b100 M
b100 *
b100 /
b100 ;
b100 K
b100 O
b0 +
b0 0
b0 <
b0 L
#64001
b100 !"
#65000
b1 +
b1 0
b1 <
b1 L
#66000
b10 +
b10 0
b10 <
b10 L
#67000
b11 +
b11 0
b11 <
b11 L
#68000
b100 +
b100 0
b100 <
b100 L
#69000
b101 +
b101 0
b101 <
b101 L
#70000
b110 +
b110 0
b110 <
b110 L
#71000
b111 +
b111 0
b111 <
b111 L
#72000
b1000 +
b1000 0
b1000 <
b1000 L
#73000
b1001 +
b1001 0
b1001 <
b1001 L
#74000
b1010 +
b1010 0
b1010 <
b1010 L
#75000
b1011 +
b1011 0
b1011 <
b1011 L
#76000
b1100 +
b1100 0
b1100 <
b1100 L
#77000
b1101 +
b1101 0
b1101 <
b1101 L
#78000
b1110 +
b1110 0
b1110 <
b1110 L
#79000
b1111 +
b1111 0
b1111 <
b1111 L
#80000
b101 $
b101 4
b101 8
b101 3
b101 :
b101 S
1_
1`
0a
1]
b101 5
b101 D
b101 F
b101 R
b101 X
b101 B
b101 G
b101 M
b101 *
b101 /
b101 ;
b101 K
b101 O
b0 +
b0 0
b0 <
b0 L
#80001
b101 !"
#81000
b1 +
b1 0
b1 <
b1 L
#82000
b10 +
b10 0
b10 <
b10 L
#83000
b11 +
b11 0
b11 <
b11 L
#84000
b100 +
b100 0
b100 <
b100 L
#85000
b101 +
b101 0
b101 <
b101 L
#86000
b110 +
b110 0
b110 <
b110 L
#87000
b111 +
b111 0
b111 <
b111 L
#88000
b1000 +
b1000 0
b1000 <
b1000 L
#89000
b1001 +
b1001 0
b1001 <
b1001 L
#90000
b1010 +
b1010 0
b1010 <
b1010 L
#91000
b1011 +
b1011 0
b1011 <
b1011 L
#92000
b1100 +
b1100 0
b1100 <
b1100 L
#93000
b1101 +
b1101 0
b1101 <
b1101 L
#94000
b1110 +
b1110 0
b1110 <
b1110 L
#95000
b1111 +
b1111 0
b1111 <
b1111 L
#96000
b110 $
b110 4
b110 8
b110 3
b110 :
b110 S
0_
0`
1a
1h
1i
0j
0]
1f
b110 5
b110 D
b110 F
b110 R
b110 X
b110 B
b110 G
b110 M
b110 *
b110 /
b110 ;
b110 K
b110 O
b0 +
b0 0
b0 <
b0 L
#96001
b110 !"
#97000
b1 +
b1 0
b1 <
b1 L
#98000
b10 +
b10 0
b10 <
b10 L
#99000
b11 +
b11 0
b11 <
b11 L
#100000
b100 +
b100 0
b100 <
b100 L
#101000
b101 +
b101 0
b101 <
b101 L
#102000
b110 +
b110 0
b110 <
b110 L
#103000
b111 +
b111 0
b111 <
b111 L
#104000
b1000 +
b1000 0
b1000 <
b1000 L
#105000
b1001 +
b1001 0
b1001 <
b1001 L
#106000
b1010 +
b1010 0
b1010 <
b1010 L
#107000
b1011 +
b1011 0
b1011 <
b1011 L
#108000
b1100 +
b1100 0
b1100 <
b1100 L
#109000
b1101 +
b1101 0
b1101 <
b1101 L
#110000
b1110 +
b1110 0
b1110 <
b1110 L
#111000
b1111 +
b1111 0
b1111 <
b1111 L
#112000
b111 $
b111 4
b111 8
b111 3
b111 :
b111 S
1_
1`
0a
1]
b111 5
b111 D
b111 F
b111 R
b111 X
b111 B
b111 G
b111 M
b111 *
b111 /
b111 ;
b111 K
b111 O
b0 +
b0 0
b0 <
b0 L
#112001
b111 !"
#113000
b1 +
b1 0
b1 <
b1 L
#114000
b10 +
b10 0
b10 <
b10 L
#115000
b11 +
b11 0
b11 <
b11 L
#116000
b100 +
b100 0
b100 <
b100 L
#117000
b101 +
b101 0
b101 <
b101 L
#118000
b110 +
b110 0
b110 <
b110 L
#119000
b111 +
b111 0
b111 <
b111 L
#120000
b1000 +
b1000 0
b1000 <
b1000 L
#121000
b1001 +
b1001 0
b1001 <
b1001 L
#122000
b1010 +
b1010 0
b1010 <
b1010 L
#123000
b1011 +
b1011 0
b1011 <
b1011 L
#124000
b1100 +
b1100 0
b1100 <
b1100 L
#125000
b1101 +
b1101 0
b1101 <
b1101 L
#126000
b1110 +
b1110 0
b1110 <
b1110 L
#127000
b1111 +
b1111 0
b1111 <
b1111 L
#128000
1"
b1000 $
b1000 4
b1000 8
b1000 3
b1000 :
b1000 S
0_
0`
1a
0h
0i
1j
0q
0r
1s
1z
1{
0|
0]
0f
0o
1x
b1000 5
b1000 D
b1000 F
b1000 R
b1000 X
b1000 B
b1000 G
b1000 M
b1000 *
b1000 /
b1000 ;
b1000 K
b1000 O
b0 +
b0 0
b0 <
b0 L
#128001
1#"
b1000 !"
#129000
b1 +
b1 0
b1 <
b1 L
#130000
b10 +
b10 0
b10 <
b10 L
#131000
b11 +
b11 0
b11 <
b11 L
#132000
b100 +
b100 0
b100 <
b100 L
#133000
b101 +
b101 0
b101 <
b101 L
#134000
b110 +
b110 0
b110 <
b110 L
#135000
b111 +
b111 0
b111 <
b111 L
#136000
b1000 +
b1000 0
b1000 <
b1000 L
#137000
b1001 +
b1001 0
b1001 <
b1001 L
#138000
b1010 +
b1010 0
b1010 <
b1010 L
#139000
b1011 +
b1011 0
b1011 <
b1011 L
#140000
b1100 +
b1100 0
b1100 <
b1100 L
#141000
b1101 +
b1101 0
b1101 <
b1101 L
#142000
b1110 +
b1110 0
b1110 <
b1110 L
#143000
b1111 +
b1111 0
b1111 <
b1111 L
#144000
b1001 $
b1001 4
b1001 8
b1001 3
b1001 :
b1001 S
1_
1`
0a
1]
b1001 5
b1001 D
b1001 F
b1001 R
b1001 X
b1001 B
b1001 G
b1001 M
b1001 *
b1001 /
b1001 ;
b1001 K
b1001 O
b0 +
b0 0
b0 <
b0 L
#144001
b1001 !"
#145000
b1 +
b1 0
b1 <
b1 L
#146000
b10 +
b10 0
b10 <
b10 L
#147000
b11 +
b11 0
b11 <
b11 L
#148000
b100 +
b100 0
b100 <
b100 L
#149000
b101 +
b101 0
b101 <
b101 L
#150000
b110 +
b110 0
b110 <
b110 L
#151000
b111 +
b111 0
b111 <
b111 L
#152000
b1000 +
b1000 0
b1000 <
b1000 L
#153000
b1001 +
b1001 0
b1001 <
b1001 L
#154000
b1010 +
b1010 0
b1010 <
b1010 L
#155000
b1011 +
b1011 0
b1011 <
b1011 L
#156000
b1100 +
b1100 0
b1100 <
b1100 L
#157000
b1101 +
b1101 0
b1101 <
b1101 L
#158000
b1110 +
b1110 0
b1110 <
b1110 L
#159000
b1111 +
b1111 0
b1111 <
b1111 L
#160000
b1010 $
b1010 4
b1010 8
b1010 3
b1010 :
b1010 S
0_
0`
1a
1h
1i
0j
0]
1f
b1010 5
b1010 D
b1010 F
b1010 R
b1010 X
b1010 B
b1010 G
b1010 M
b1010 *
b1010 /
b1010 ;
b1010 K
b1010 O
b0 +
b0 0
b0 <
b0 L
#160001
b1010 !"
#161000
b1 +
b1 0
b1 <
b1 L
#162000
b10 +
b10 0
b10 <
b10 L
#163000
b11 +
b11 0
b11 <
b11 L
#164000
b100 +
b100 0
b100 <
b100 L
#165000
b101 +
b101 0
b101 <
b101 L
#166000
b110 +
b110 0
b110 <
b110 L
#167000
b111 +
b111 0
b111 <
b111 L
#168000
b1000 +
b1000 0
b1000 <
b1000 L
#169000
b1001 +
b1001 0
b1001 <
b1001 L
#170000
b1010 +
b1010 0
b1010 <
b1010 L
#171000
b1011 +
b1011 0
b1011 <
b1011 L
#172000
b1100 +
b1100 0
b1100 <
b1100 L
#173000
b1101 +
b1101 0
b1101 <
b1101 L
#174000
b1110 +
b1110 0
b1110 <
b1110 L
#175000
b1111 +
b1111 0
b1111 <
b1111 L
#176000
b1011 $
b1011 4
b1011 8
b1011 3
b1011 :
b1011 S
1_
1`
0a
1]
b1011 5
b1011 D
b1011 F
b1011 R
b1011 X
b1011 B
b1011 G
b1011 M
b1011 *
b1011 /
b1011 ;
b1011 K
b1011 O
b0 +
b0 0
b0 <
b0 L
#176001
b1011 !"
#177000
b1 +
b1 0
b1 <
b1 L
#178000
b10 +
b10 0
b10 <
b10 L
#179000
b11 +
b11 0
b11 <
b11 L
#180000
b100 +
b100 0
b100 <
b100 L
#181000
b101 +
b101 0
b101 <
b101 L
#182000
b110 +
b110 0
b110 <
b110 L
#183000
b111 +
b111 0
b111 <
b111 L
#184000
b1000 +
b1000 0
b1000 <
b1000 L
#185000
b1001 +
b1001 0
b1001 <
b1001 L
#186000
b1010 +
b1010 0
b1010 <
b1010 L
#187000
b1011 +
b1011 0
b1011 <
b1011 L
#188000
b1100 +
b1100 0
b1100 <
b1100 L
#189000
b1101 +
b1101 0
b1101 <
b1101 L
#190000
b1110 +
b1110 0
b1110 <
b1110 L
#191000
b1111 +
b1111 0
b1111 <
b1111 L
#192000
b1100 $
b1100 4
b1100 8
b1100 3
b1100 :
b1100 S
0_
0`
1a
0h
0i
1j
1q
1r
0s
0]
0f
1o
b1100 5
b1100 D
b1100 F
b1100 R
b1100 X
b1100 B
b1100 G
b1100 M
b1100 *
b1100 /
b1100 ;
b1100 K
b1100 O
b0 +
b0 0
b0 <
b0 L
#192001
b1100 !"
#193000
b1 +
b1 0
b1 <
b1 L
#194000
b10 +
b10 0
b10 <
b10 L
#195000
b11 +
b11 0
b11 <
b11 L
#196000
b100 +
b100 0
b100 <
b100 L
#197000
b101 +
b101 0
b101 <
b101 L
#198000
b110 +
b110 0
b110 <
b110 L
#199000
b111 +
b111 0
b111 <
b111 L
#200000
b1000 +
b1000 0
b1000 <
b1000 L
#201000
b1001 +
b1001 0
b1001 <
b1001 L
#202000
b1010 +
b1010 0
b1010 <
b1010 L
#203000
b1011 +
b1011 0
b1011 <
b1011 L
#204000
b1100 +
b1100 0
b1100 <
b1100 L
#205000
b1101 +
b1101 0
b1101 <
b1101 L
#206000
b1110 +
b1110 0
b1110 <
b1110 L
#207000
b1111 +
b1111 0
b1111 <
b1111 L
#208000
b1101 $
b1101 4
b1101 8
b1101 3
b1101 :
b1101 S
1_
1`
0a
1]
b1101 5
b1101 D
b1101 F
b1101 R
b1101 X
b1101 B
b1101 G
b1101 M
b1101 *
b1101 /
b1101 ;
b1101 K
b1101 O
b0 +
b0 0
b0 <
b0 L
#208001
b1101 !"
#209000
b1 +
b1 0
b1 <
b1 L
#210000
b10 +
b10 0
b10 <
b10 L
#211000
b11 +
b11 0
b11 <
b11 L
#212000
b100 +
b100 0
b100 <
b100 L
#213000
b101 +
b101 0
b101 <
b101 L
#214000
b110 +
b110 0
b110 <
b110 L
#215000
b111 +
b111 0
b111 <
b111 L
#216000
b1000 +
b1000 0
b1000 <
b1000 L
#217000
b1001 +
b1001 0
b1001 <
b1001 L
#218000
b1010 +
b1010 0
b1010 <
b1010 L
#219000
b1011 +
b1011 0
b1011 <
b1011 L
#220000
b1100 +
b1100 0
b1100 <
b1100 L
#221000
b1101 +
b1101 0
b1101 <
b1101 L
#222000
b1110 +
b1110 0
b1110 <
b1110 L
#223000
b1111 +
b1111 0
b1111 <
b1111 L
#224000
b1110 $
b1110 4
b1110 8
b1110 3
b1110 :
b1110 S
0_
0`
1a
1h
1i
0j
0]
1f
b1110 5
b1110 D
b1110 F
b1110 R
b1110 X
b1110 B
b1110 G
b1110 M
b1110 *
b1110 /
b1110 ;
b1110 K
b1110 O
b0 +
b0 0
b0 <
b0 L
#224001
b1110 !"
#225000
b1 +
b1 0
b1 <
b1 L
#226000
b10 +
b10 0
b10 <
b10 L
#227000
b11 +
b11 0
b11 <
b11 L
#228000
b100 +
b100 0
b100 <
b100 L
#229000
b101 +
b101 0
b101 <
b101 L
#230000
b110 +
b110 0
b110 <
b110 L
#231000
b111 +
b111 0
b111 <
b111 L
#232000
b1000 +
b1000 0
b1000 <
b1000 L
#233000
b1001 +
b1001 0
b1001 <
b1001 L
#234000
b1010 +
b1010 0
b1010 <
b1010 L
#235000
b1011 +
b1011 0
b1011 <
b1011 L
#236000
b1100 +
b1100 0
b1100 <
b1100 L
