Estructura_de_Computadores/Practica_01/mux2_4.v
//Multiplexor 2 a 1.
module mux2_4(output wire [3:0] Out, input wire [3:0] A, input wire [3:0] B, input wire s);
//Asignación a Out dependiendo del valor de s para obtener B o A.
assign Out = (s)?B:A;
endmodule

2/Estructura_de_Computadores/Practica_01_modificacion/mux4_1.v
//Multiplexor 4 a 1
module mux4_1(output reg out, input wire a, b, c, d, input wire [1:0] S);

 always@(a,b,c,d,S)
 begin
  case(S)
    2'b00: out = a;
    2'b01: out = b;
    2'b10: out = c;
    2'b11: out = d;
  endcase
 end
endmodule

2/Estructura_de_Computadores/Practica_01_modificacion/cl.v
// Declaración del módulo de la Celda lógica
module cl(output wire out, input wire a, b, input wire [1:0] S);
// Declaramos los wire para que los operadores lógicos tengan una salida
wire wire1,wire2,wire3,wire4;
// Creación de operador lógico and
and and1(wire1 ,a, b);
// Creación de operador lógico or
or or1(wire2, a, b);
// Creación de operador lógico xor
xor xor1(wire3, a, b);
// Creación de operador lógico not
not not1(wire4,b);
// Implementamos el multiplexor 4 a 1 con los wire
mux4_1 mux4_1_1(out, wire1, wire2, wire3, wire4,S);

endmodule

2/Estructura_de_Computadores/Practica_01_modificacion/ul4.v
// Unidad lógica de 4 bits
module ul4(output wire[3:0] Out, input wire[3:0] A, input wire[3:0] B, input wire [1:0] S);
  //Primera celda lógica
  cl cl1(Out[0],A[0],B[0],S);
  //Segunda celda lógica
  cl cl2(Out[1],A[1],B[1],S);
  //Tercera celda lógica
  cl cl3(Out[2],A[2],B[2],S);
  //Cuarta celda lógica
  cl cl4(Out[3],A[3],B[3],S);

endmodule

2º/Estructura_de_Computadores/Practica_01_modificacion/fa.v
//Declaración del módulo del Sumador completo
module fa(output wire c_out, sum, input wire a, b, c_in);
// Asignación continua de c_out y sum dado por la suma de a + b + c_in.
assign {c_out,sum} = a + b + c_in;

endmodule

2/Estructura_de_Computadores/Practica_01/sum4.v
//Sumador completo de tipo estructural
module sum4(output wire[3:0] S, output wire c_out, input wire[3:0] A, input wire[3:0] B, input wire c_in);
// Declaración de los wire
wire C1,C2,C3;
// Sumador completo del primer bit
fa fa1(C1,S[0],A[0],B[0],c_in);
// Sumador completo del segundo bit
fa fa2(C2,S[1],A[1],B[1],C1);
// Sumador completo del tercer bit
fa fa3(C3,S[2],A[2],B[2],C2);
// Sumador completo del cuarto bit
fa fa4(c_out,S[3],A[3],B[3],C3);

endmodule

2/Estructura_de_Computadores/Practica_01_modificacion/control.v
module control(output wire add1, op1_A, op2_B,cpl, input wire[2:0]Op);
//Función lógica de add1
assign add1 = ((~Op[2] & Op[1]) | (~Op[0]));
//Función lógica de op1_A
assign op1_A = (Op[1] & ~Op[0]) | (Op[2] & ~Op[1]);
//Función lógica de op2_B
assign op2_B = (Op[1] & ~Op[0]) | (Op[2] & ~Op[1]);
//Función lógica de cpl
assign cpl = (~Op[2] & ~Op[1] & ~Op[0]);

endmodule

Estructura_de_Computadores/Practica_01_modificacion/cpl1.v
// Declaración del módulo de complemento a 1.
module cpl1(output wire [3:0] Out, input wire [3:0] Inp, input wire cpl);
/* Asignación continua de Out dependiendo si cpl es 1 o 0 para que se invierta o no 
los bits de Inp.*/
assign Out = (cpl == 1)? ~Inp : Inp;

endmodule

Estructura_de_Computadores/Practica_01_modificacion/preprocess.v
module preprocess(output wire [3:0] AMod, output wire [3:0] BMod, input wire [3:0] A,
input wire [3:0] B, input wire [2:0] Op);
// Declaración de los wire de 1 bit
wire add1,op1_A,op2_B,cpl;
// Declaración de los wire de 4 bits
wire[3:0] wiremux1, wiremux2;
/*Llamada al multiplexor 2 a 1 de 4 bits
IN: 0 ,1; OUT: wiremux1; señal de control: add1 
*/
mux2_4 mux2_1(wiremux1,4'b0000,4'b0001,add1);
/*Llamada al multiplexor 2 a 1 de 4 bits
IN: A, B; OUT: wiremux2; señal de control: op2_B 
*/
mux2_4 mux2_2(wiremux2,A,B,op2_B);
/*Llamada al multiplexor 2 a 1 de 4 bits
IN: A , wiremux1; OUT: AMod; señal de control: op1_A 
*/
mux2_4 mux2_3(AMod,wiremux1,A,op1_A);
/*Llamada al complementario a 1.
IN: wiremux2; OUT: BMod; señal de control: cpl
*/
cpl1   cpl_1(BMod,wiremux2,cpl);
/*Llamada al modulo de control
IN: Op ; OUT: add1, op1_A, op2_B, cpl
*/
control control_1(add1, op1_A, op2_B, cpl, Op);

endmodule

Estructura_de_Computadores/Practica_01_modificacion/alu.v
// Declaración del módulo alu
module alu(output wire [3:0] R, output wire zero, carry, sign, input wire [3:0] A, B, input wire c_in,
input wire [2:0] Op);
// Declaración los wire de 4 bits.
wire[3:0] OP1,OP2,sum4_wire,ul4_wire;
//Llamada al módulo preprocess.
preprocess preprocess_1(OP1,OP2,A,B,Op);
//Llamada al módulo sum4(sumador de 4 bits).
sum4 sum4_1(sum4_wire,carry,OP1,OP2,c_in);
//Llamada al módulo ul(unidad lógica).
ul4  ul4_1(ul4_wire,OP1,OP2,Op[1:0]);
//Llamada al módulo mux2_4(Multiplexor 2 a 1 de 4 bits).
mux2_4 mux2_4_1(R,sum4_wire,ul4_wire,Op[2]);
//Asignación zero a 1 si R == 0.
assign zero = (R == 4'b0000);
//Asignación sign al primer bit de R.
assign sign = (R[3]);

endmodule

Estructura_de_Computadores/Practica_01_modificacion/alu_tb_modPE104.v
// Testbench para modulo alu
`timescale 1 ns / 10 ps //Directiva que fija la unidad de tiempo de simulación y la precision de la unidad
module alu_tb;
//declaracion de señales
reg [2:0] t_Op;
reg t_cin;
reg [3:0] t_A, t_B; 
wire [3:0] t_R;
wire t_z, t_c, t_s;
integer errores;

// error de cualquier tipo, de resultado, de linea zero, de signo y carry
reg error, error_R, error_z, error_s, error_c; 

//instancia del modulo a testear
alu mat(t_R, t_z, t_c, t_s, t_A, t_B, t_cin, t_Op);


initial
begin
	$dumpfile("alu_mod.vcd");
	$dumpvars;

	errores = 0;
	
	t_Op = 3'b000;
	repeat(8)
	begin
		t_cin = 1'b0;
		repeat(2)
		begin
			t_A = 4'b0;
			repeat(16) 
			begin
				t_B = 4'b0;
				repeat(16) 
				begin
					#0.01 check;
					#9.99;
					t_B = t_B + 1;
				end
				t_A = t_A + 1;
			end
			t_cin = t_cin + 1;
		end
		t_Op = t_Op + 1;
	end
	$display("Encontradas %d operaciones erroneas", errores);
  	//fin simulacion
  	$finish;
end

// Tarea para hacer la comprobación automática de resultados
task check;
reg [4:0] expected_R;
reg expected_z, expected_c, expected_s;

begin
	$write("tiempo=%0d A=%b B=%b c_in=%b OP=%b R=%b, Z=%b, C=%b, S=%b.", $time, t_A, t_B, t_cin, t_Op, t_R, t_z, t_c, t_s);
	case (t_Op)	
		3'b000: expected_R = (t_A ^4'b1111) + 4'b0001 + t_cin;
		3'b001: expected_R = t_A + t_cin;
		3'b010: expected_R = t_A + t_B + t_cin;
		3'b011: expected_R = t_A + 1 + t_cin;
		3'b100: expected_R = t_A & t_B;
		3'b101: expected_R = t_A | t_B;
		3'b110: expected_R = t_A ^ t_B;
		3'b111: expected_R[3:0] = ~t_A;
		default: $display("ERROR. Valor no esperado para t_Op: %b", t_Op);
	endcase
	if (t_Op[2]) // Si la operación es lógica
	begin
		expected_c = 1'b0;
		expected_s = expected_R[3];
		error_s = 0;
	 	error_c = 0;
	end
	else
	begin
		expected_c = expected_R[4];
		expected_s = expected_R[3];
		error_s = (expected_s !== t_s);
	 	error_c = (expected_c !== t_c);
	end

	expected_z = ~| expected_R[3:0];
	// generacion señales error generales para toda la ALU
	error_R = (expected_R[3:0] !== t_R); 
	error_z = (expected_z !== t_z);
	error = error_R | error_z | error_s | error_c;
	if (error)
	begin
		errores = errores + 1;
		$display(" ---- ERROR");
		if (error_R)
			$display("\tResultado esperado %b, obtenido %b", expected_R[3:0], t_R);
		if (error_z)
			$display("\tFlag de cero esperado %b, obtenido %b", expected_z, t_z);
		if (error_s)
			$display("\tFlag de signo esperado %b, obtenido %b", expected_s, t_s);
		if (error_c)
			$display("\tFlag de acarreo esperado %b, obtenido %b", expected_c, t_c);
	end
	else
		$display(" ---- OK");
end
endtask
endmodule

Estructura_de_Computadores/Practica_01_modificacion/alu_mod.vcd
$date
	Mon Oct 21 08:52:25 2024
$end
$version
	Icarus Verilog
$end
$timescale
	10ps
$end
$scope module alu_tb $end
$var wire 1 ! t_z $end
$var wire 1 " t_s $end
$var wire 1 # t_c $end
$var wire 4 $ t_R [3:0] $end
$var reg 1 % error $end
$var reg 1 & error_R $end
$var reg 1 ' error_c $end
$var reg 1 ( error_s $end
$var reg 1 ) error_z $end
$var reg 4 * t_A [3:0] $end
$var reg 4 + t_B [3:0] $end
$var reg 3 , t_Op [2:0] $end
$var reg 1 - t_cin $end
$var integer 32 . errores [31:0] $end
$scope module mat $end
$var wire 4 / A [3:0] $end
$var wire 4 0 B [3:0] $end
$var wire 3 1 Op [2:0] $end
$var wire 1 - c_in $end
$var wire 1 ! zero $end
$var wire 4 2 ul4_wire [3:0] $end
$var wire 4 3 sum4_wire [3:0] $end
$var wire 1 " sign $end
$var wire 1 # carry $end
$var wire 4 4 R [3:0] $end
$var wire 4 5 OP2 [3:0] $end
$var wire 4 6 OP1 [3:0] $end
$scope module mux2_4_1 $end
$var wire 1 7 s $end
$var wire 4 8 Out [3:0] $end
$var wire 4 9 B [3:0] $end
$var wire 4 : A [3:0] $end
$upscope $end
$scope module preprocess_1 $end
$var wire 4 ; A [3:0] $end
$var wire 4 < B [3:0] $end
$var wire 3 = Op [2:0] $end
$var wire 4 > wiremux2 [3:0] $end
$var wire 4 ? wiremux1 [3:0] $end
$var wire 1 @ op2_B $end
$var wire 1 A op1_A $end
$var wire 1 B cpl $end
$var wire 1 C add1 $end
$var wire 4 D BMod [3:0] $end
$var wire 4 E AMod [3:0] $end
$scope module control_1 $end
$var wire 3 F Op [2:0] $end
$var wire 1 C add1 $end
$var wire 1 B cpl $end
$var wire 1 A op1_A $end
$var wire 1 @ op2_B $end
$upscope $end
$scope module cpl_1 $end
$var wire 1 B cpl $end
$var wire 4 G Out [3:0] $end
$var wire 4 H Inp [3:0] $end
$upscope $end
$scope module mux2_1 $end
$var wire 4 I A [3:0] $end
$var wire 4 J B [3:0] $end
$var wire 1 C s $end
$var wire 4 K Out [3:0] $end
$upscope $end
$scope module mux2_2 $end
$var wire 4 L A [3:0] $end
$var wire 4 M B [3:0] $end
$var wire 1 @ s $end
$var wire 4 N Out [3:0] $end
$upscope $end
$scope module mux2_3 $end
$var wire 4 O A [3:0] $end
$var wire 4 P B [3:0] $end
$var wire 1 A s $end
$var wire 4 Q Out [3:0] $end
$upscope $end
$upscope $end
$scope module sum4_1 $end
$var wire 4 R A [3:0] $end
$var wire 4 S B [3:0] $end
$var wire 1 - c_in $end
$var wire 1 # c_out $end
$var wire 4 T S [3:0] $end
$var wire 1 U C3 $end
$var wire 1 V C2 $end
$var wire 1 W C1 $end
$scope module fa1 $end
$var wire 1 X a $end
$var wire 1 Y b $end
$var wire 1 - c_in $end
$var wire 1 Z sum $end
$var wire 1 W c_out $end
$upscope $end
$scope module fa2 $end
$var wire 1 [ a $end
$var wire 1 \ b $end
$var wire 1 W c_in $end
$var wire 1 ] sum $end
$var wire 1 V c_out $end
$upscope $end
$scope module fa3 $end
$var wire 1 ^ a $end
$var wire 1 _ b $end
$var wire 1 V c_in $end
$var wire 1 ` sum $end
$var wire 1 U c_out $end
$upscope $end
$scope module fa4 $end
$var wire 1 a a $end
$var wire 1 b b $end
$var wire 1 U c_in $end
$var wire 1 c sum $end
$var wire 1 # c_out $end
$upscope $end
$upscope $end
$scope module ul4_1 $end
$var wire 4 d A [3:0] $end
$var wire 4 e B [3:0] $end
$var wire 2 f S [1:0] $end
$var wire 4 g Out [3:0] $end
$scope module cl1 $end
$var wire 2 h S [1:0] $end
$var wire 1 i a $end
$var wire 1 j b $end
$var wire 1 k wire1 $end
$var wire 1 l wire2 $end
$var wire 1 m wire3 $end
$var wire 1 n wire4 $end
$var wire 1 o out $end
$scope module mux4_1_1 $end
$var wire 2 p S [1:0] $end
$var wire 1 k a $end
$var wire 1 l b $end
$var wire 1 m c $end
$var wire 1 n d $end
$var reg 1 o out $end
$upscope $end
$upscope $end
$scope module cl2 $end
$var wire 2 q S [1:0] $end
$var wire 1 r a $end
$var wire 1 s b $end
$var wire 1 t wire1 $end
$var wire 1 u wire2 $end
$var wire 1 v wire3 $end
$var wire 1 w wire4 $end
$var wire 1 x out $end
$scope module mux4_1_1 $end
$var wire 2 y S [1:0] $end
$var wire 1 t a $end
$var wire 1 u b $end
$var wire 1 v c $end
$var wire 1 w d $end
$var reg 1 x out $end
$upscope $end
$upscope $end
$scope module cl3 $end
$var wire 2 z S [1:0] $end
$var wire 1 { a $end
$var wire 1 | b $end
$var wire 1 } wire1 $end
$var wire 1 ~ wire2 $end
$var wire 1 !" wire3 $end
$var wire 1 "" wire4 $end
$var wire 1 #" out $end
$scope module mux4_1_1 $end
$var wire 2 $" S [1:0] $end
$var wire 1 } a $end
$var wire 1 ~ b $end
$var wire 1 !" c $end
$var wire 1 "" d $end
$var reg 1 #" out $end
$upscope $end
$upscope $end
$scope module cl4 $end
$var wire 2 %" S [1:0] $end
$var wire 1 &" a $end
$var wire 1 '" b $end
$var wire 1 (" wire1 $end
$var wire 1 )" wire2 $end
$var wire 1 *" wire3 $end
$var wire 1 +" wire4 $end
$var wire 1 ," out $end
$scope module mux4_1_1 $end
$var wire 2 -" S [1:0] $end
$var wire 1 (" a $end
$var wire 1 )" b $end
$var wire 1 *" c $end
$var wire 1 +" d $end
$var reg 1 ," out $end
$upscope $end
$upscope $end
$upscope $end
$upscope $end
$scope task check $end
$var reg 5 ." expected_R [4:0] $end
$var reg 1 /" expected_c $end
$var reg 1 0" expected_s $end
$var reg 1 1" expected_z $end
$upscope $end
$upscope $end
$enddefinitions $end
$comment Show the parameter values. $end
$dumpall
$end
#0
$dumpvars
x1"
x0"
x/"
bx ."
b0 -"
0,"
0+"
1*"
1)"
0("
1'"
0&"
b0 %"
b0 $"
0#"
0""
1!"
1~
0}
1|
0{
b0 z
b0 y
0x
0w
1v
1u
0t
1s
0r
b0 q
b0 p
1o
0n
0m
1l
1k
1j
1i
b0 h
b1 g
b0 f
b1111 e
b1 d
0c
1b
0a
0`
1_
0^
0]
1\
0[
0Z
1Y
1X
1W
1V
1U
b0 T
b1111 S
b1 R
b1 Q
b0 P
b1 O
b0 N
b0 M
b0 L
b1 K
b1 J
b0 I
b0 H
b1111 G
b0 F
b1 E
b1111 D
1C
1B
0A
0@
b1 ?
b0 >
b0 =
b0 <
b0 ;
b0 :
b1 9
b0 8
07
b1 6
b1111 5
b0 4
b0 3
b1 2
b0 1
b0 0
b0 /
b0 .
0-
b0 ,
b0 +
b0 *
x)
x(
x'
x&
x%
b0 $
1#
0"
1!
$end
#1
0%
0)
0&
11"
0'
0(
00"
1/"
b10000 ."
#1000
b1 +
b1 0
b1 <
b1 M
#2000
b10 +
b10 0
b10 <
b10 M
#3000
b11 +
b11 0
b11 <
b11 M
#4000
b100 +
b100 0
b100 <
b100 M
#5000
b101 +
b101 0
b101 <
b101 M
#6000
b110 +
b110 0
b110 <
b110 M
#7000
b111 +
b111 0
b111 <
b111 M
#8000
b1000 +
b1000 0
b1000 <
b1000 M
#9000
b1001 +
b1001 0
b1001 <
b1001 M
#10000
b1010 +
b1010 0
b1010 <
b1010 M
#11000
b1011 +
b1011 0
b1011 <
b1011 M
#12000
b1100 +
b1100 0
b1100 <
b1100 M
#13000
b1101 +
b1101 0
b1101 <
b1101 M
#14000
b1110 +
b1110 0
b1110 <
b1110 M
#15000
b1111 +
b1111 0
b1111 <
b1111 M
#16000
1"
1c
0#
1`
0U
0!
b1111 $
b1111 4
b1111 8
1]
0V
b0 2
b0 9
b0 g
0o
b1111 3
b1111 :
b1111 T
1Z
0W
0k
1m
1n
0Y
0j
b1110 5
b1110 D
b1110 G
b1110 S
b1110 e
b1 >
b1 H
b1 N
b1 *
b1 /
b1 ;
b1 L
b1 P
b0 +
b0 0
b0 <
b0 M
#16001
01"
10"
0/"
b1111 ."
#17000
b1 +
b1 0
b1 <
b1 M
#18000
b10 +
b10 0
b10 <
b10 M
#19000
b11 +
b11 0
b11 <
b11 M
#20000
b100 +
b100 0
b100 <
b100 M
#21000
b101 +
b101 0
b101 <
b101 M
#22000
b110 +
b110 0
b110 <
b110 M
#23000
b111 +
b111 0
b111 <
b111 M
#24000
b1000 +
b1000 0
b1000 <
b1000 M
#25000
b1001 +
b1001 0
b1001 <
b1001 M
#26000
b1010 +
b1010 0
b1010 <
b1010 M
#27000
b1011 +
b1011 0
b1011 <
b1011 M
#28000
b1100 +
b1100 0
b1100 <
b1100 M
#29000
b1101 +
b1101 0
b1101 <
b1101 M
#30000
b1110 +
b1110 0
b1110 <
b1110 M
#31000
b1111 +
b1111 0
b1111 <
b1111 M
#32000
b1110 $
b1110 4
b1110 8
b1 2
b1 9
b1 g
1o
0Z
1W
b1110 3
b1110 :
b1110 T
1]
1k
0m
0n
0u
0v
1w
1Y
0\
1j
0s
b1101 5
b1101 D
b1101 G
b1101 S
b1101 e
b10 >
b10 H
b10 N
b10 *
b10 /
b10 ;
b10 L
b10 P
b0 +
b0 0
b0 <
b0 M
#32001
b1110 ."
#33000
b1 +
b1 0
b1 <
b1 M
#34000
b10 +
b10 0
b10 <
b10 M
#35000
b11 +
b11 0
b11 <
b11 M
#36000
b100 +
b100 0
b100 <
b100 M
#37000
b101 +
b101 0
b101 <
b101 M
#38000
b110 +
b110 0
b110 <
b110 M
#39000
b111 +
b111 0
b111 <
b111 M
#40000
b1000 +
b1000 0
b1000 <
b1000 M
#41000
b1001 +
b1001 0
b1001 <
b1001 M
#42000
b1010 +
b1010 0
b1010 <
b1010 M
#43000
b1011 +
b1011 0
b1011 <
b1011 M
#44000
b1100 +
b1100 0
b1100 <
b1100 M
#45000
b1101 +
b1101 0
b1101 <
b1101 M
#46000
b1110 +
b1110 0
b1110 <
b1110 M
#47000
b1111 +
b1111 0
b1111 <
b1111 M
#48000
b1101 $
b1101 4
b1101 8
0]
b0 2
b0 9
b0 g
0o
b1101 3
b1101 :
b1101 T
1Z
0W
0k
1m
1n
0Y
0j
b1100 5
b1100 D
b1100 G
b1100 S
b1100 e
b11 >
b11 H
b11 N
b11 *
b11 /
b11 ;
b11 L
b11 P
b0 +
b0 0
b0 <
b0 M
#48001
b1101 ."
#49000
b1 +
b1 0
b1 <
b1 M
#50000
b10 +
b10 0
b10 <
b10 M
#51000
b11 +
b11 0
b11 <
b11 M
#52000
b100 +
b100 0
b100 <
b100 M
#53000
b101 +
b101 0
b101 <
b101 M
#54000
b110 +
b110 0
b110 <
b110 M
#55000
b111 +
b111 0
b111 <
b111 M
#56000
b1000 +
b1000 0
b1000 <
b1000 M
#57000
b1001 +
b1001 0
b1001 <
b1001 M
#58000
b1010 +
b1010 0
b1010 <
b1010 M
#59000
b1011 +
b1011 0
b1011 <
b1011 M
#60000
b1100 +
b1100 0
b1100 <
b1100 M
#61000
b1101 +
b1101 0
b1101 <
b1101 M
#62000
b1110 +
b1110 0
b1110 <
b1110 M
#63000
b1111 +
b1111 0
b1111 <
b1111 M
#64000
1V
b1100 $
b1100 4
b1100 8
b1 2
b1 9
b1 g
1o
0Z
1W
0]
b1100 3
b1100 :
b1100 T
1`
1k
0m
0n
1u
1v
0w
0~
0!"
1""
1Y
1\
0_
1j
1s
0|
b1011 5
b1011 D
b1011 G
b1011 S
b1011 e
b100 >
b100 H
b100 N
b100 *
b100 /
b100 ;
b100 L
b100 P
b0 +
b0 0
b0 <
b0 M
#64001
b1100 ."
#65000
b1 +
b1 0
b1 <
b1 M
#66000
b10 +
b10 0
b10 <
b10 M
#67000
b11 +
b11 0
b11 <
b11 M
#68000
b100 +
b100 0
b100 <
b100 M
#69000
b101 +
b101 0
b101 <
b101 M
#70000
b110 +
b110 0
b110 <
b110 M
#71000
b111 +
b111 0
b111 <
b111 M
#72000
b1000 +
b1000 0
b1000 <
b1000 M
#73000
b1001 +
b1001 0
b1001 <
b1001 M
#74000
b1010 +
b1010 0
b1010 <
b1010 M
#75000
b1011 +
b1011 0
b1011 <
b1011 M
#76000
b1100 +
b1100 0
b1100 <
b1100 M
#77000
b1101 +
b1101 0
b1101 <
b1101 M
#78000
b1110 +
b1110 0
b1110 <
b1110 M
#79000
b1111 +
b1111 0
b1111 <
b1111 M
#80000
0`
b1011 $
b1011 4
b1011 8
1]
0V
b0 2
b0 9
b0 g
0o
b1011 3
b1011 :
b1011 T
1Z
0W
0k
1m
1n
0Y
0j
b1010 5
b1010 D
b1010 G
b1010 S
b1010 e
b101 >
b101 H
b101 N
b101 *
b101 /
b101 ;
b101 L
b101 P
b0 +
b0 0
b0 <
b0 M
#80001
b1011 ."
#81000
b1 +
b1 0
b1 <
b1 M
#82000
b10 +
b10 0
b10 <
b10 M
#83000
b11 +
b11 0
b11 <
b11 M
#84000
b100 +
b100 0
b100 <
b100 M
#85000
b101 +
b101 0
b101 <
b101 M
#86000
b110 +
b110 0
b110 <
b110 M
#87000
b111 +
b111 0
b111 <
b111 M
#88000
b1000 +
b1000 0
b1000 <
b1000 M
#89000
b1001 +
b1001 0
b1001 <
b1001 M
#90000
b1010 +
b1010 0
b1010 <
b1010 M
#91000
b1011 +
b1011 0
b1011 <
b1011 M
#92000
b1100 +
b1100 0
b1100 <
b1100 M
#93000
b1101 +
b1101 0
b1101 <
b1101 M
#94000
b1110 +
b1110 0
b1110 <
b1110 M
#95000
b1111 +
b1111 0
b1111 <
b1111 M
#96000
b1010 $
b1010 4
b1010 8
b1 2
b1 9
b1 g
1o
0Z
1W
b1010 3
b1010 :
b1010 T
1]
1k
0m
0n
0u
0v
1w
1Y
0\
1j
0s
b1001 5
b1001 D
b1001 G
b1001 S
b1001 e
b110 >
b110 H
b110 N
b110 *
b110 /
b110 ;
b110 L
b110 P
b0 +
b0 0
b0 <
b0 M
#96001
b1010 ."
#97000
b1 +
b1 0
b1 <
b1 M
#98000
b10 +
b10 0
b10 <
b10 M
#99000
b11 +
b11 0
b11 <
b11 M
#100000
b100 +
b100 0
b100 <
b100 M
#101000
b101 +
b101 0
b101 <
b101 M
#102000
b110 +
b110 0
b110 <
b110 M
#103000
b111 +
b111 0
b111 <
b111 M
#104000
b1000 +
b1000 0
b1000 <
b1000 M
#105000
b1001 +
b1001 0
b1001 <
b1001 M
#106000
b1010 +
b1010 0
b1010 <
b1010 M
#107000
b1011 +
b1011 0
b1011 <
b1011 M
#108000
b1100 +
b1100 0
b1100 <
b1100 M
#109000
b1101 +
b1101 0
b1101 <
b1101 M
#110000
b1110 +
b1110 0
b1110 <
b1110 M
#111000
b1111 +
b1111 0
b1111 <
b1111 M
#112000
b1001 $
b1001 4
b1001 8
0]
b0 2
b0 9
b0 g
0o
b1001 3
b1001 :
b1001 T
1Z
0W
0k
1m
1n
0Y
0j
b1000 5
b1000 D
b1000 G
b1000 S
b1000 e
b111 >
b111 H
b111 N
b111 *
b111 /
b111 ;
b111 L
b111 P
b0 +
b0 0
b0 <
b0 M
#112001
b1001 ."
#113000
b1 +
b1 0
b1 <
b1 M
#114000
b10 +
b10 0
b10 <
b10 M
#115000
b11 +
b11 0
b11 <
b11 M
#116000
b100 +
b100 0
b100 <
b100 M
#117000
b101 +
b101 0
b101 <
b101 M
#118000
b110 +
b110 0
b110 <
b110 M
#119000
b111 +
b111 0
b111 <
b111 M
#120000
b1000 +
b1000 0
b1000 <
b1000 M
#121000
b1001 +
b1001 0
b1001 <
b1001 M
#122000
b1010 +
b1010 0
b1010 <
b1010 M
#123000
b1011 +
b1011 0
b1011 <
b1011 M
#124000
b1100 +
b1100 0
b1100 <
b1100 M
#125000
b1101 +
b1101 0
b1101 <
b1101 M
#126000
b1110 +
b1110 0
b1110 <
b1110 M
#127000
b1111 +
b1111 0
b1111 <
b1111 M
#128000
0!
1U
1"
1V
b1000 $
b1000 4
b1000 8
b1 2
b1 9
b1 g
1o
0Z
1W
0]
0`
b1000 3
b1000 :
b1000 T
1c
1k
0m
0n
1u
1v
0w
1~
1!"
0""
0)"
0*"
1+"
1Y
1\
1_
0b
1j
1s
1|
0'"
b111 5
b111 D
b111 G
b111 S
b111 e
b1000 >
b1000 H
b1000 N
b1000 *
b1000 /
b1000 ;
b1000 L
b1000 P
b0 +
b0 0
b0 <
b0 M
#128001
b1000 ."
#129000
b1 +
b1 0
b1 <
b1 M
#130000
b10 +
b10 0
b10 <
b10 M
#131000
b11 +
b11 0
b11 <
b11 M
#132000
b100 +
b100 0
b100 <
b100 M
#133000
b101 +
b101 0
b101 <
b101 M
#134000
b110 +
b110 0
b110 <
b110 M
#135000
b111 +
b111 0
b111 <
b111 M
#136000
b1000 +
b1000 0
b1000 <
b1000 M
#137000
b1001 +
b1001 0
b1001 <
b1001 M
#138000
b1010 +
b1010 0
b1010 <
b1010 M
#139000
b1011 +
b1011 0
b1011 <
b1011 M
#140000
b1100 +
b1100 0
b1100 <
b1100 M
#141000
b1101 +
b1101 0
b1101 <
b1101 M
#142000
b1110 +
b1110 0
b1110 <
b1110 M
#143000
b1111 +
b1111 0
b1111 <
b1111 M
#144000
0"
0c
1`
0U
b111 $
b111 4
b111 8
1]
0V
b0 2
b0 9
b0 g
0o
b111 3
b111 :
b111 T
1Z
0W
0k
1m
1n
0Y
0j
b110 5
b110 D
b110 G
b110 S
b110 e
b1001 >
b1001 H
b1001 N
b1001 *
b1001 /
b1001 ;
b1001 L
b1001 P
b0 +
b0 0
b0 <
b0 M
#144001
00"
b111 ."
#145000
b1 +
b1 0
b1 <
b1 M
#146000
b10 +
b10 0
b10 <
b10 M
#147000
b11 +
b11 0
b11 <
b11 M
#148000
b100 +
b100 0
b100 <
b100 M
#149000
b101 +
b101 0
b101 <
b101 M
#150000
b110 +
b110 0
b110 <
b110 M
#151000
b111 +
b111 0
b111 <
b111 M
#152000
b1000 +
b1000 0
b1000 <
b1000 M
#153000
b1001 +
b1001 0
b1001 <
b1001 M
#154000
b1010 +
b1010 0
b1010 <
b1010 M
#155000
b1011 +
b1011 0
b1011 <
b1011 M
#156000
b1100 +
b1100 0
b1100 <
b1100 M
#157000
b1101 +
b1101 0
b1101 <
b1101 M
#158000
b1110 +
b1110 0
b1110 <
b1110 M
#159000
b1111 +
b1111 0
b1111 <
b1111 M
#160000
b110 $
b110 4
b110 8
b1 2
b1 9
b1 g
1o
0Z
1W
b110 3
b110 :
b110 T
1]
1k
0m
0n
0u
0v
1w
1Y
0\
1j
0s
b101 5
b101 D
b101 G
b101 S
b101 e
b1010 >
b1010 H
b1010 N
b1010 *
b1010 /
b1010 ;
b1010 L
b1010 P
b0 +
b0 0
b0 <
b0 M
#160001
b110 ."
#161000
b1 +
b1 0
b1 <
b1 M
#162000
b10 +
b10 0
b10 <
b10 M
#163000
b11 +
b11 0
b11 <
b11 M
#164000
b100 +
b100 0
b100 <
b100 M
#165000
b101 +
b101 0
b101 <
b101 M
#166000
b110 +
b110 0
b110 <
b110 M
#167000
b111 +
b111 0
b111 <
b111 M
#168000
b1000 +
b1000 0
b1000 <
b1000 M
#169000
b1001 +
b1001 0
b1001 <
b1001 M
#170000
b1010 +
b1010 0
b1010 <
b1010 M
#171000
b1011 +
b1011 0
b1011 <
b1011 M
#172000
b1100 +
b1100 0
b1100 <
b1100 M
#173000
b1101 +
b1101 0
b1101 <
b1101 M
#174000
b1110 +
b1110 0
b1110 <
b1110 M
#175000
b1111 +
b1111 0
b1111 <
b1111 M
#176000
b101 $
b101 4
b101 8
0]
b0 2
b0 9
b0 g
0o
b101 3
b101 :
b101 T
1Z
0W
0k
1m
1n
0Y
0j
b100 5
b100 D
b100 G
b100 S
b100 e
b1011 >
b1011 H
b1011 N
b1011 *
b1011 /
b1011 ;
b1011 L
b1011 P
b0 +
b0 0
b0 <
b0 M
#176001
b101 ."
#177000
b1 +
b1 0
b1 <
b1 M
#178000
b10 +
b10 0
b10 <
b10 M
#179000
b11 +
b11 0
b11 <
b11 M
#180000
b100 +
b100 0
b100 <
b100 M
#181000
b101 +
b101 0
b101 <
b101 M
#182000
b110 +
b110 0
b110 <
b110 M
#183000
b111 +
b111 0
b111 <
b111 M
#184000
b1000 +
b1000 0
b1000 <
b1000 M
#185000
b1001 +
b1001 0
b1001 <
b1001 M
#186000
b1010 +
b1010 0
b1010 <
b1010 M
#187000
b1011 +
b1011 0
b1011 <
b1011 M
#188000
b1100 +
b1100 0
b1100 <
b1100 M
#189000
b1101 +
b1101 0
b1101 <
b1101 M
#190000
b1110 +
b1110 0
b1110 <
b1110 M
#191000
b1111 +
b1111 0
b1111 <
b1111 M
#192000
1V
b100 $
b100 4
b100 8
b1 2
b1 9
b1 g
1o
0Z
1W
0]
b100 3
b100 :
b100 T
1`
1k
0m
0n
1u
1v
0w
0~
0!"
1""
1Y
1\
0_
1j
1s
0|
b11 5
b11 D
b11 G
b11 S
b11 e
b1100 >
b1100 H
b1100 N
b1100 *
b1100 /
b1100 ;
b1100 L
b1100 P
b0 +
b0 0
b0 <
b0 M
#192001
b100 ."
#193000
b1 +
b1 0
b1 <
b1 M
#194000
b10 +
b10 0
b10 <
b10 M
#195000
b11 +
b11 0
b11 <
b11 M
#196000
b100 +
b100 0
b100 <
b100 M
#197000
b101 +
b101 0
b101 <
b101 M
#198000
b110 +
b110 0
b110 <
b110 M
#199000
b111 +
b111 0
b111 <
b111 M
#200000
b1000 +
b1000 0
b1000 <
b1000 M
#201000
b1001 +
b1001 0
b1001 <
b1001 M
#202000
b1010 +
b1010 0
b1010 <
b1010 M
#203000
b1011 +
b1011 0
b1011 <
b1011 M
#204000
b1100 +
b1100 0
b1100 <
b1100 M
